Workbook
Name Slicer_Country: #N/A
Name Slicer_Rating_Category: #N/A
Name Slicer_Release_year: #N/A
Name Slicer_Type: #N/A

Sheet Movie vs Shows
A3: Row Labels | B3: Count of Show_id
A4: Movie | B4: 0.97240991
A5: TV Show | B5: 0.02759009

Sheet Country-wise content
A3: Row Labels | B3: Count of Title
A4: United States | B4: 1846
A5: India | B5: 875
A6: United Kingdom | B6: 183
A7: Canada | B7: 107
A8: Spain | B8: 91
A9: Egypt | B9: 89
A10: Nigeria | B10: 88
A11: Japan | B11: 83
A12: Turkey | B12: 79
A13: Indonesia | B13: 76

Sheet Release_Trend
A3: Row Labels | B3: Count of Title
A4: 2021 | B4: 161
A5: 2012 | B5: 163
A6: 2013 | B6: 197
A7: 2014 | B7: 242
A8: 2015 | B8: 349
A9: 2020 | B9: 442
A10: 2019 | B10: 519
A11: 2016 | B11: 576
A12: 2018 | B12: 647
A13: 2017 | B13: 656

Sheet Rating_Distribution
A3: Row Labels | B3: Count of Show_id
A4: Adult | B4: 0.48817568
A5: Family | B5: 0.15578078
A6: Kids | B6: 0.029091592
A7: Not Rated | B7: 0.011448949
A8: Teen | B8: 0.315503

Sheet Dashboard
D1: Netflix Content Distribution
A2: ='Top country'!A4 -> United States
A6: =COUNTA(Table1[Show_id]) -> 5328
A10: =COUNTIF(Table1[Type],"Movie") -> 5181
A14: =COUNTIF(Table1[Type],"Tv Show") -> 147
A18: =COUNTA(_xlfn.UNIQUE(Table1[Country])) -> 603
A22: =ROUND(AVERAGE(Table1[Release_year]),0) -> 2013

Sheet Top country
A3: Row Labels | B3: Count of Show_id
A4: United States | B4: 1846

Sheet Netflix_Dataset
A1: Show_id | B1: Type | C1: Title | D1: Director | E1: Cast | F1: Country | G1: Date_added | H1: Year_Added | I1: Release_year | J1: Content age(years) | K1: Rating | L1: Rating Category | M1: Recommendation | N1: Duration | O1: Duration Category | P1: Listed_in
A2: s8 | B2: Movie | C2: Sankofa | D2: Haile Gerima | E2: Kofi Ghanaba, Oyafunmike Ogunlano, Alexandra Duah, Nick Medley, Mutabaruka, Afemo Omilami, Reggie Carter, Mzuri | F2: United States, Ghana, Burkina Faso, United Kingdom, Germany, Ethiopia | G2: September 1, 2021 | H2: 2021 | I2: 1993 | J2: =YEAR(TODAY())-Table1[[#This Row],[Release_year]] -> 33 | K2: TV-MA | L2: =_xlfn.XLOOKUP(Table1[[#This Row],[Rating]],Ratings!A$2:A$15,Ratings!B$2:B$15) -> Adult | M2: =_xlfn.XLOOKUP(Table1[[#This Row],[Rating Category]],Recommendation!A$2:A$6,Recommendation!B$2:B$6) -> Restricted | N2: 125 | O2: {=_xlfn.IFS(Table1[[#This Row],[Duration]]<90,"Short",Table1[[#This Row],[Duration]]<180,"Medium",Table1[[#This Row],[Duration]]<=240,"Long",TRUE,"Seasons")} -> Medium | P2: Dramas, Independent Movies, International Movies
A3: s9 | B3: TV Show | C3: The Great British Baking Show | D3: Andy Devonshire | E3: Mel Giedroyc, Sue Perkins, Mary Berry, Paul Hollywood | F3: United Kingdom | G3: September 24, 2021 | H3: 2021 | I3: 2021 | J3: =YEAR(TODAY())-Table1[[#This Row],[Release_year]] -> 5 | K3: TV-14 | L3: =_xlfn.XLOOKUP(Table1[[#This Row],[Rating]],Ratings!A$2:A$15,Ratings!B$2:B$15) -> Teen | M3: =_xlfn.XLOOKUP(Table1[[#This Row],[Rating Category]],Recommendation!A$2:A$6,Recommendation!B$2:B$6) -> Guidance | N3: 9 Seasons | O3: {=_xlfn.IFS(Table1[[#This Row],[Duration]]<90,"Short",Table1[[#This Row],[Duration]]<180,"Medium",Table1[[#This Row],[Duration]]<=240,"Long",TRUE,"Seasons")} -> Seasons | P3: British TV Shows, Reality TV
A4: s10 | B4: Movie | C4: The Starling | D4: Theodore Melfi | E4: Melissa McCarthy, Chris O'Dowd, Kevin Kline, Timothy Olyphant, Daveed Diggs, Skyler Gisondo, Laura Harrier, Rosalind Chao, Kimberly Quinn, Loretta Devine, Ravi Kapoor | F4: United States | G4: September 24, 2021 | H4: 2021 | I4: 2021 | J4: =YEAR(TODAY())-Table1[[#This Row],[Release_year]] -> 5 | K4: PG-13 | L4: =_xlfn.XLOOKUP(Table1[[#This Row],[Rating]],Ratings!A$2:A$15,Ratings!B$2:B$15) -> Teen | M4: =_xlfn.XLOOKUP(Table1[[#This Row],[Rating Category]],Recommendation!A$2:A$6,Recommendation!B$2:B$6) -> Guidance | N4: 104 | O4: {=_xlfn.IFS(Table1[[#This Row],[Duration]]<90,"Short",Table1[[#This Row],[Duration]]<180,"Medium",Table1[[#This Row],[Duration]]<=240,"Long",TRUE,"Seasons")} -> Medium | P4: Comedies, Dramas
A5: s13 | B5: Movie | C5: Je Suis Karl | D5: Christian Schwochow | E5: Luna Wedler, Jannis Niewhner, Milan Peschel, Edin Hasanovi, Anna Fialov, Marlon Boess, Victor Boccard, Fleur Geffrier, Aziz Dyab, Mlanie Fouch, Elizaveta Maximov | F5: Germany, Czech Republic | G5: September 23, 2021 | H5: 2021 | I5: 2021 | J5: =YEAR(TODAY())-Table1[[#This Row],[Release_year]] -> 5 | K5: TV-MA | L5: =_xlfn.XLOOKUP(Table1[[#This Row],[Rating]],Ratings!A$2:A$15,Ratings!B$2:B$15) -> Adult | M5: =_xlfn.XLOOKUP(Table1[[#This Row],[Rating Category]],Recommendation!A$2:A$6,Recommendation!B$2:B$6) -> Restricted | N5: 127 | O5: {=_xlfn.IFS(Table1[[#This Row],[Duration]]<90,"Short",Table1[[#This Row],[Duration]]<180,"Medium",Table1[[#This Row],[Duration]]<=240,"Long",TRUE,"Seasons")} -> Medium | P5: Dramas, International Movies
A6: s25 | B6: Movie | C6: Jeans | D6: S. Shankar | E6: Prashanth, Aishwarya Rai Bachchan, Sri Lakshmi, Nassar | F6: India | G6: September 21, 2021 | H6: 2021 | I6: 1998 | J6: =YEAR(TODAY())-Table1[[#This Row],[Release_year]] -> 28 | K6: TV-14 | L6: =_xlfn.XLOOKUP(Table1[[#This Row],[Rating]],Ratings!A$2:A$15,Ratings!B$2:B$15) -> Teen | M6: =_xlfn.XLOOKUP(Table1[[#This Row],[Rating Category]],Recommendation!A$2:A$6,Recommendation!B$2:B$6) -> Guidance | N6: 166 | O6: {=_xlfn.IFS(Table1[[#This Row],[Duration]]<90,"Short",Table1[[#This Row],[Duration]]<180,"Medium",Table1[[#This Row],[Duration]]<=240,"Long",TRUE,"Seasons")} -> Medium | P6: Comedies, International Movies, Romantic Movies
A7: s28 | B7: Movie | C7: Grown Ups | D7: Dennis Dugan | E7: Adam Sandler, Kevin James, Chris Rock, David Spade, Rob Schneider, Salma Hayek, Maria Bello, Maya Rudolph, Colin Quinn, Tim Meadows, Joyce Van Patten | F7: United States | G7: September 20, 2021 | H7: 2021 | I7: 2010 | J7: =YEAR(TODAY())-Table1[[#This Row],[Release_year]] -> 16 | K7: PG-13 | L7: =_xlfn.XLOOKUP(Table1[[#This Row],[Rating]],Ratings!A$2:A$15,Ratings!B$2:B$15) -> Teen | M7: =_xlfn.XLOOKUP(Table1[[#This Row],[Rating Category]],Recommendation!A$2:A$6,Recommendation!B$2:B$6) -> Guidance | N7: 103 | O7: {=_xlfn.IFS(Table1[[#This Row],[Duration]]<90,"Short",Table1[[#This Row],[Duration]]<180,"Medium",Table1[[#This Row],[Duration]]<=240,"Long",TRUE,"Seasons")} -> Medium | P7: Comedies
A8: s29 | B8: Movie | C8: Dark Skies | D8: Scott Stewart | E8: Keri Russell, Josh Hamilton, J.K. Simmons, Dakota Goyo, Kadan Rockett, L.J. Benet, Rich Hutchman, Myndy Crist, Annie Thurman, Jake Brennan | F8: United States | G8: September 19, 2021 | H8: 2021 | I8: 2013 | J8: =YEAR(TODAY())-Table1[[#This Row],[Release_year]] -> 13 | K8: PG-13 | L8: =_xlfn.XLOOKUP(Table1[[#This Row],[Rating]],Ratings!A$2:A$15,Ratings!B$2:B$15) -> Teen | M8: =_xlfn.XLOOKUP(Table1[[#This Row],[Rating Category]],Recommendation!A$2:A$6,Recommendation!B$2:B$6) -> Guidance | N8: 97 | O8: {=_xlfn.IFS(Table1[[#This Row],[Duration]]<90,"Short",Table1[[#This Row],[Duration]]<180,"Medium",Table1[[#This Row],[Duration]]<=240,"Long",TRUE,"Seasons")} -> Medium | P8: Horror Movies, Sci-Fi & Fantasy
A9: s30 | B9: Movie | C9: Paranoia | D9: Robert Luketic | E9: Liam Hemsworth, Gary Oldman, Amber Heard, Harrison Ford, Lucas Till, Embeth Davidtz, Julian McMahon, Josh Holloway, Richard Dreyfuss, Angela Sarafyan | F9: United States, India, France | G9: September 19, 2021 | H9: 2021 | I9: 2013 | J9: =YEAR(TODAY())-Table1[[#This Row],[Release_year]] -> 13 | K9: PG-13 | L9: =_xlfn.XLOOKUP(Table1[[#This Row],[Rating]],Ratings!A$2:A$15,Ratings!B$2:B$15) -> Teen | M9: =_xlfn.XLOOKUP(Table1[[#This Row],[Rating Category]],Recommendation!A$2:A$6,Recommendation!B$2:B$6) -> Guidance | N9: 106 | O9: {=_xlfn.IFS(Table1[[#This Row],[Duration]]<90,"Short",Table1[[#This Row],[Duration]]<180,"Medium",Table1[[#This Row],[Duration]]<=240,"Long",TRUE,"Seasons")} -> Medium | P9: Thrillers
A10: s39 | B10: Movie | C10: Birth of the Dragon | D10: George Nolfi | E10: Billy Magnussen, Ron Yuan, Qu Jingjing, Terry Chen, Vanness Wu, Jin Xing, Philip Ng, Xia Yu, Yu Xia | F10: China, Canada, United States | G10: September 16, 2021 | H10: 2021 | I10: 2017 | J10: =YEAR(TODAY())-Table1[[#This Row],[Release_year]] -> 9 | K10: PG-13 | L10: =_xlfn.XLOOKUP(Table1[[#This Row],[Rating]],Ratings!A$2:A$15,Ratings!B$2:B$15) -> Teen | M10: =_xlfn.XLOOKUP(Table1[[#This Row],[Rating Category]],Recommendation!A$2:A$6,Recommendation!B$2:B$6) -> Guidance | N10: 96 | O10: {=_xlfn.IFS(Table1[[#This Row],[Duration]]<90,"Short",Table1[[#This Row],[Duration]]<180,"Medium",Table1[[#This Row],[Duration]]<=240,"Long",TRUE,"Seasons")} -> Medium | P10: Action & Adventure, Dramas
A11: s42 | B11: Movie | C11: Jaws | D11: Steven Spielberg | E11: Roy Scheider, Robert Shaw, Richard Dreyfuss, Lorraine Gary, Murray Hamilton, Carl Gottlieb, Jeffrey Kramer, Susan Backlinie, Jonathan Filley, Ted Grossman | F11: United States | G11: September 16, 2021 | H11: 2021 | I11: 1975 | J11: =YEAR(TODAY())-Table1[[#This Row],[Release_year]] -> 51 | K11: PG | L11: =_xlfn.XLOOKUP(Table1[[#This Row],[Rating]],Ratings!A$2:A$15,Ratings!B$2:B$15) -> Family | M11: =_xlfn.XLOOKUP(Table1[[#This Row],[Rating Category]],Recommendation!A$2:A$6,Recommendation!B$2:B$6) -> Guidance | N11: 124 | O11: {=_xlfn.IFS(Table1[[#This Row],[Duration]]<90,"Short",Table1[[#This Row],[Duration]]<180,"Medium",Table1[[#This Row],[Duration]]<=240,"Long",TRUE,"Seasons")} -> Medium | P11: Action & Adventure, Classic Movies, Dramas
A12: s43 | B12: Movie | C12: Jaws 2 | D12: Jeannot Szwarc | E12: Roy Scheider, Lorraine Gary, Murray Hamilton, Joseph Mascolo, Jeffrey Kramer, Collin Wilcox Paxton, Ann Dusenberry, Mark Gruner, Barry Coe, Susan French | F12: United States | G12: September 16, 2021 | H12: 2021 | I12: 1978 | J12: =YEAR(TODAY())-Table1[[#This Row],[Release_year]] -> 48 | K12: PG | L12: =_xlfn.XLOOKUP(Table1[[#This Row],[Rating]],Ratings!A$2:A$15,Ratings!B$2:B$15) -> Family | M12: =_xlfn.XLOOKUP(Table1[[#This Row],[Rating Category]],Recommendation!A$2:A$6,Recommendation!B$2:B$6) -> Guidance | N12: 116 | O12: {=_xlfn.IFS(Table1[[#This Row],[Duration]]<90,"Short",Table1[[#This Row],[Duration]]<180,"Medium",Table1[[#This Row],[Duration]]<=240,"Long",TRUE,"Seasons")} -> Medium | P12: Dramas, Horror Movies, Thrillers
A13: s44 | B13: Movie | C13: Jaws 3 | D13: Joe Alves | E13: Dennis Quaid, Bess Armstrong, Simon MacCorkindale, Louis Gossett Jr., John Putch, Lea Thompson, P.H. Moriarty, Dan Blasko, Liz Morris, Lisa Maurer | F13: United States | G13: September 16, 2021 | H13: 2021 | I13: 1983 | J13: =YEAR(TODAY())-Table1[[#This Row],[Release_year]] -> 43 | K13: PG | L13: =_xlfn.XLOOKUP(Table1[[#This Row],[Rating]],Ratings!A$2:A$15,Ratings!B$2:B$15) -> Family | M13: =_xlfn.XLOOKUP(Table1[[#This Row],[Rating Category]],Recommendation!A$2:A$6,Recommendation!B$2:B$6) -> Guidance | N13: 98 | O13: {=_xlfn.IFS(Table1[[#This Row],[Duration]]<90,"Short",Table1[[#This Row],[Duration]]<180,"Medium",Table1[[#This Row],[Duration]]<=240,"Long",TRUE,"Seasons")} -> Medium | P13: Action & Adventure, Horror Movies, Thrillers
A14: s45 | B14: Movie | C14: Jaws: The Revenge | D14: Joseph Sargent | E14: Lorraine Gary, Lance Guest, Mario Van Peebles, Karen Young, Michael Caine, Judith Barsi, Mitchell Anderson, Lynn Whitfield | F14: United States | G14: September 16, 2021 | H14: 2021 | I14: 1987 | J14: =YEAR(TODAY())-Table1[[#This Row],[Release_year]] -> 39 | K14: PG-13 | L14: =_xlfn.XLOOKUP(Table1[[#This Row],[Rating]],Ratings!A$2:A$15,Ratings!B$2:B$15) -> Teen | M14: =_xlfn.XLOOKUP(Table1[[#This Row],[Rating Category]],Recommendation!A$2:A$6,Recommendation!B$2:B$6) -> Guidance | N14: 91 | O14: {=_xlfn.IFS(Table1[[#This Row],[Duration]]<90,"Short",Table1[[#This Row],[Duration]]<180,"Medium",Table1[[#This Row],[Duration]]<=240,"Long",TRUE,"Seasons")} -> Medium | P14: Action & Adventure, Horror Movies, Thrillers
A15: s47 | B15: Movie | C15: Safe House | D15: Daniel Espinosa | E15: Denzel Washington, Ryan Reynolds, Vera Farmiga, Brendan Gleeson, Sam Shepard, Rubn Blades, Nora Arnezeder, Robert Patrick, Liam Cunningham, Joel Kinnaman | F15: South Africa, United States, Japan | G15: September 16, 2021 | H15: 2021 | I15: 2012 | J15: =YEAR(TODAY())-Table1[[#This Row],[Release_year]] -> 14 | K15: R | L15: =_xlfn.XLOOKUP(Table1[[#This Row],[Rating]],Ratings!A$2:A$15,Ratings!B$2:B$15) -> Adult | M15: =_xlfn.XLOOKUP(Table1[[#This Row],[Rating Category]],Recommendation!A$2:A$6,Recommendation!B$2:B$6) -> Restricted | N15: 115 | O15: {=_xlfn.IFS(Table1[[#This Row],[Duration]]<90,"Short",Table1[[#This Row],[Duration]]<180,"Medium",Table1[[#This Row],[Duration]]<=240,"Long",TRUE,"Seasons")} -> Medium | P15: Action & Adventure
... A93: s196 | B93: Movie | C93: EMI: Liya Hai To Chukana Padega | D93: Saurabh Kabra | E93: Sanjay Dutt, Arjun Rampal, Malaika Arora, Aashish Chaudhary, Neha Uberoi, Urmila Matondkar, Manoj Joshi, Daya Shankar Pandey, Pushkar Jog, Kulbhushan Kharbanda | F93: India | G93: August 27, 2021 | H93: 2021 | I93: 2008 | J93: =YEAR(TODAY())-Table1[[#This Row],[Release_year]] -> 18 | K93: TV-14 | L93: =_xlfn.XLOOKUP(Table1[[#This Row],[Rating]],Ratings!A$2:A$15,Ratings!B$2:B$15) -> Teen | M93: =_xlfn.XLOOKUP(Table1[[#This Row],[Rating Category]],Recommendation!A$2:A$6,Recommendation!B$2:B$6) -> Guidance | N93: 128 | O93: {=_xlfn.IFS(Table1[[#This Row],[Duration]]<90,"Short",Table1[[#This Row],[Duration]]<180,"Medium",Table1[[#This Row],[Duration]]<=240,"Long",TRUE,"Seasons")} -> Medium | P93: Comedies, Dramas, International Movies
A94: s199 | B94: TV Show | C94: King of Boys: The Return of the King | D94: Kemi Adetiba | E94: Sola Sobowale, Toni Tones, Richard Mofe-Damijo, Efa Iwara, Titi Kuti, Tobechukwu "iLLbliss" Ejiofor, Remilekun "Reminisce" Safaru, Charles "Charly Boy" Oputa, Nse Ikpe-Etim, Keppy Ekpenyong Bassey, Bimbo Manuel, Akin Lewis, Lord Frank, Osas Ighodaro, Taiwo Ajai-Lycett, Paul Sambo | F94: Nigeria | G94: August 27, 2021 | H94: 2021 | I94: 2021 | J94: =YEAR(TODAY())-Table1[[#This Row],[Release_year]] -> 5 | K94: TV-MA | L94: =_xlfn.XLOOKUP(Table1[[#This Row],[Rating]],Ratings!A$2:A$15,Ratings!B$2:B$15) -> Adult | M94: =_xlfn.XLOOKUP(Table1[[#This Row],[Rating Category]],Recommendation!A$2:A$6,Recommendation!B$2:B$6) -> Restricted | N94: 1 Season | O94: {=_xlfn.IFS(Table1[[#This Row],[Duration]]<90,"Short",Table1[[#This Row],[Duration]]<180,"Medium",Table1[[#This Row],[Duration]]<=240,"Long",TRUE,"Seasons")} -> Seasons | P94: Crime TV Shows, International TV Shows, TV Dramas
A95: s200 | B95: Movie | C95: Koi Aap Sa | D95: Partho Mitra | E95: Aftab Shivdasani, Natassha, Dipannita Sharma, Himanshu Mallik, Vaidya Advai, Pushy Anand, Shama Deshpande, Rajendra Gupta | F95: India | G95: August 27, 2021 | H95: 2021 | I95: 2006 | J95: =YEAR(TODAY())-Table1[[#This Row],[Release_year]] -> 20 | K95: TV-14 | L95: =_xlfn.XLOOKUP(Table1[[#This Row],[Rating]],Ratings!A$2:A$15,Ratings!B$2:B$15) -> Teen | M95: =_xlfn.XLOOKUP(Table1[[#This Row],[Rating Category]],Recommendation!A$2:A$6,Recommendation!B$2:B$6) -> Guidance | N95: 135 | O95: {=_xlfn.IFS(Table1[[#This Row],[Duration]]<90,"Short",Table1[[#This Row],[Duration]]<180,"Medium",Table1[[#This Row],[Duration]]<=240,"Long",TRUE,"Seasons")} -> Medium | P95: Comedies, Dramas, International Movies
A96: s201 | B96: Movie | C96: Krishna Cottage | D96: Santram Varma | E96: Sohail Khan, Isha Koppikar, Natassha, Rati Agnihotri, Vrajesh Hirjee, Divya Palat, Hiten Tejwani, Rajendranath Zutshi | F96: India | G96: August 27, 2021 | H96: 2021 | I96: 2004 | J96: =YEAR(TODAY())-Table1[[#This Row],[Release_year]] -> 22 | K96: TV-14 | L96: =_xlfn.XLOOKUP(Table1[[#This Row],[Rating]],Ratings!A$2:A$15,Ratings!B$2:B$15) -> Teen | M96: =_xlfn.XLOOKUP(Table1[[#This Row],[Rating Category]],Recommendation!A$2:A$6,Recommendation!B$2:B$6) -> Guidance | N96: 124 | O96: {=_xlfn.IFS(Table1[[#This Row],[Duration]]<90,"Short",Table1[[#This Row],[Duration]]<180,"Medium",Table1[[#This Row],[Duration]]<=240,"Long",TRUE,"Seasons")} -> Medium | P96: Action & Adventure, Horror Movies, International Movies
A97: s202 | B97: Movie | C97: Kucch To Hai | D97: Anil V. Kumar, Anurag Basu | E97: Tusshar Kapoor, Esha Deol, Natassha, Vrajesh Hirjee, Kusumit Sana, Rishi Kapoor, Moon Moon Sen, Johny Lever, Ashay Chitre, Jeetendra | F97: India | G97: August 27, 2021 | H97: 2021 | I97: 2003 | J97: =YEAR(TODAY())-Table1[[#This Row],[Release_year]] -> 23 | K97: TV-14 | L97: =_xlfn.XLOOKUP(Table1[[#This Row],[Rating]],Ratings!A$2:A$15,Ratings!B$2:B$15) -> Teen | M97: =_xlfn.XLOOKUP(Table1[[#This Row],[Rating Category]],Recommendation!A$2:A$6,Recommendation!B$2:B$6) -> Guidance | N97: 136 | O97: {=_xlfn.IFS(Table1[[#This Row],[Duration]]<90,"Short",Table1[[#This Row],[Duration]]<180,"Medium",Table1[[#This Row],[Duration]]<=240,"Long",TRUE,"Seasons")} -> Medium | P97: Dramas, International Movies, Thrillers
A98: s203 | B98: Movie | C98: Kyaa Kool Hai Hum | D98: Sangeeth Sivan | E98: Tusshar Kapoor, Riteish Deshmukh, Isha Koppikar, Neha Dhupia, Anupam Kher, Jay Sean | F98: India | G98: August 27, 2021 | H98: 2021 | I98: 2005 | J98: =YEAR(TODAY())-Table1[[#This Row],[Release_year]] -> 21 | K98: TV-MA | L98: =_xlfn.XLOOKUP(Table1[[#This Row],[Rating]],Ratings!A$2:A$15,Ratings!B$2:B$15) -> Adult | M98: =_xlfn.XLOOKUP(Table1[[#This Row],[Rating Category]],Recommendation!A$2:A$6,Recommendation!B$2:B$6) -> Restricted | N98: 165 | O98: {=_xlfn.IFS(Table1[[#This Row],[Duration]]<90,"Short",Table1[[#This Row],[Duration]]<180,"Medium",Table1[[#This Row],[Duration]]<=240,"Long",TRUE,"Seasons")} -> Medium | P98: Comedies, International Movies, Music & Musicals
A99: s204 | B99: Movie | C99: Kyaa Kool Hain Hum 3 | D99: Umesh Ghadge | E99: Tusshar Kapoor, Aftab Shivdasani, Krishna Abhishek, Mandana Karimi, Shakti Kapoor, Darshan Jariwala, Sushmita Mukherjee, Meghna Naidu, Anand Kumar, Claudia Ciesla | F99: India | G99: August 27, 2021 | H99: 2021 | I99: 2016 | J99: =YEAR(TODAY())-Table1[[#This Row],[Release_year]] -> 10 | K99: TV-MA | L99: =_xlfn.XLOOKUP(Table1[[#This Row],[Rating]],Ratings!A$2:A$15,Ratings!B$2:B$15) -> Adult | M99: =_xlfn.XLOOKUP(Table1[[#This Row],[Rating Category]],Recommendation!A$2:A$6,Recommendation!B$2:B$6) -> Restricted | N99: 124 | O99: {=_xlfn.IFS(Table1[[#This Row],[Duration]]<90,"Short",Table1[[#This Row],[Duration]]<180,"Medium",Table1[[#This Row],[Duration]]<=240,"Long",TRUE,"Seasons")} -> Medium | P99: Comedies, International Movies
A100: s205 | B100: Movie | C100: Kyaa Super Kool Hain Hum | D100: Sachin Yardi | E100: Tusshar Kapoor, Riteish Deshmukh, Anupam Kher, Rohit Shetty, Neha Sharma, Chunky Pandey, Sarah-Jane Dias, Razak Khan, Kavin Dave | F100: India | G100: August 27, 2021 | H100: 2021 | I100: 2012 | J100: =YEAR(TODAY())-Table1[[#This Row],[Release_year]] -> 14 | K100: TV-MA | L100: =_xlfn.XLOOKUP(Table1[[#This Row],[Rating]],Ratings!A$2:A$15,Ratings!B$2:B$15) -> Adult | M100: =_xlfn.XLOOKUP(Table1[[#This Row],[Rating Category]],Recommendation!A$2:A$6,Recommendation!B$2:B$6) -> Restricted | N100: 136 | O100: {=_xlfn.IFS(Table1[[#This Row],[Duration]]<90,"Short",Table1[[#This Row],[Duration]]<180,"Medium",Table1[[#This Row],[Duration]]<=240,"Long",TRUE,"Seasons")} -> Medium | P100: Comedies, International Movies
A101: s206 | B101: Movie | C101: Kyo Kii... Main Jhuth Nahin Bolta | D101: David Dhawan | E101: Govinda, Sushmita Sen, Rambha, Anupam Kher, Satish Kaushik, Sharad Kapoor, Kiran Kumar, Mohnish Bahl | F101: India | G101: August 27, 2021 | H101: 2021 | I101: 2001 | J101: =YEAR(TODAY())-Table1[[#This Row],[Release_year]] -> 25 | K101: TV-14 | L101: =_xlfn.XLOOKUP(Table1[[#This Row],[Rating]],Ratings!A$2:A$15,Ratings!B$2:B$15) -> Teen | M101: =_xlfn.XLOOKUP(Table1[[#This Row],[Rating Category]],Recommendation!A$2:A$6,Recommendation!B$2:B$6) -> Guidance | N101: 150 | O101: {=_xlfn.IFS(Table1[[#This Row],[Duration]]<90,"Short",Table1[[#This Row],[Duration]]<180,"Medium",Table1[[#This Row],[Duration]]<=240,"Long",TRUE,"Seasons")} -> Medium | P101: Comedies, International Movies, Sci-Fi & Fantasy
A102: s207 | B102: Movie | C102: LSD: Love, Sex Aur Dhokha | D102: Dibakar Banerjee | E102: Nushrat Bharucha, Anshuman Jha, Neha Chauhan, Rajkummar Rao, Arya Banerjee, Amit Sial, Herry Tangri | F102: India | G102: August 27, 2021 | H102: 2021 | I102: 2010 | J102: =YEAR(TODAY())-Table1[[#This Row],[Release_year]] -> 16 | K102: TV-MA | L102: =_xlfn.XLOOKUP(Table1[[#This Row],[Rating]],Ratings!A$2:A$15,Ratings!B$2:B$15) -> Adult | M102: =_xlfn.XLOOKUP(Table1[[#This Row],[Rating Category]],Recommendation!A$2:A$6,Recommendation!B$2:B$6) -> Restricted | N102: 112 | O102: {=_xlfn.IFS(Table1[[#This Row],[Duration]]<90,"Short",Table1[[#This Row],[Duration]]<180,"Medium",Table1[[#This Row],[Duration]]<=240,"Long",TRUE,"Seasons")} -> Medium | P102: Dramas, Independent Movies, International Movies
A103: s208 | B103: Movie | C103: Mission Istaanbul: Darr Ke Aagey Jeet Hai | D103: Apoorva Lakhia | E103: Vivek Oberoi, Zayed Khan, Shriya Saran, Nikitin Dheer, Shabbir Ahluwalia, Sunil Shetty, Shweta Bhardwaj | F103: India | G103: August 27, 2021 | H103: 2021 | I103: 2008 | J103: =YEAR(TODAY())-Table1[[#This Row],[Release_year]] -> 18 | K103: TV-14 | L103: =_xlfn.XLOOKUP(Table1[[#This Row],[Rating]],Ratings!A$2:A$15,Ratings!B$2:B$15) -> Teen | M103: =_xlfn.XLOOKUP(Table1[[#This Row],[Rating Category]],Recommendation!A$2:A$6,Recommendation!B$2:B$6) -> Guidance | N103: 119 | O103: {=_xlfn.IFS(Table1[[#This Row],[Duration]]<90,"Short",Table1[[#This Row],[Duration]]<180,"Medium",Table1[[#This Row],[Duration]]<=240,"Long",TRUE,"Seasons")} -> Medium | P103: Action & Adventure, International Movies, Music & Musicals
A104: s209 | B104: Movie | C104: Once Upon a Time in Mumbaai | D104: Milan Luthria | E104: Ajay Devgn, Emraan Hashmi, Kangana Ranaut, Prachi Desai, Randeep Hooda, Naved Aslam, Asif Basra, Avtar Gill | F104: India | G104: August 27, 2021 | H104: 2021 | I104: 2010 | J104: =YEAR(TODAY())-Table1[[#This Row],[Release_year]] -> 16 | K104: TV-14 | L104: =_xlfn.XLOOKUP(Table1[[#This Row],[Rating]],Ratings!A$2:A$15,Ratings!B$2:B$15) -> Teen | M104: =_xlfn.XLOOKUP(Table1[[#This Row],[Rating Category]],Recommendation!A$2:A$6,Recommendation!B$2:B$6) -> Guidance | N104: 133 | O104: {=_xlfn.IFS(Table1[[#This Row],[Duration]]<90,"Short",Table1[[#This Row],[Duration]]<180,"Medium",Table1[[#This Row],[Duration]]<=240,"Long",TRUE,"Seasons")} -> Medium | P104: Dramas, International Movies, Music & Musicals
A105: s210 | B105: Movie | C105: Once Upon a Time in Mumbai Dobaara! | D105: Milan Luthria | E105: Akshay Kumar, Imran Khan, Sonakshi Sinha, Sonali Bendre, Sarfaraz Khan, Mahesh Manjrekar, Abhimanyu Singh, Kurush Deboo, Pitobash, Chetan Hansraj | F105: India | G105: August 27, 2021 | H105: 2021 | I105: 2013 | J105: =YEAR(TODAY())-Table1[[#This Row],[Release_year]] -> 13 | K105: TV-14 | L105: =_xlfn.XLOOKUP(Table1[[#This Row],[Rating]],Ratings!A$2:A$15,Ratings!B$2:B$15) -> Teen | M105: =_xlfn.XLOOKUP(Table1[[#This Row],[Rating Category]],Recommendation!A$2:A$6,Recommendation!B$2:B$6) -> Guidance | N105: 142 | O105: {=_xlfn.IFS(Table1[[#This Row],[Duration]]<90,"Short",Table1[[#This Row],[Duration]]<180,"Medium",Table1[[#This Row],[Duration]]<=240,"Long",TRUE,"Seasons")} -> Medium | P105: Dramas, International Movies, Music & Musicals
A106: s211 | B106: Movie | C106: Ragini MMS | D106: Pawan Kripalani | E106: Kainaz Motivala, Rajkummar Rao, Rajat Kaul, Janice, Shernaza, Mangala Ahire, Vinod Rawat | F106: India | G106: August 27, 2021 | H106: 2021 | I106: 2011 | J106: =YEAR(TODAY())-Table1[[#This Row],[Release_year]] -> 15 | K106: TV-MA | L106: =_xlfn.XLOOKUP(Table1[[#This Row],[Rating]],Ratings!A$2:A$15,Ratings!B$2:B$15) -> Adult | M106: =_xlfn.XLOOKUP(Table1[[#This Row],[Rating Category]],Recommendation!A$2:A$6,Recommendation!B$2:B$6) -> Restricted | N106: 93 | O106: {=_xlfn.IFS(Table1[[#This Row],[Duration]]<90,"Short",Table1[[#This Row],[Duration]]<180,"Medium",Table1[[#This Row],[Duration]]<=240,"Long",TRUE,"Seasons")} -> Medium | P106: Horror Movies, International Movies
... A121: s271 | B121: Movie | C121: Beckett | D121: Ferdinando Cito Filomarino | E121: John David Washington, Boyd Holbrook, Alicia Vikander, Vicky Krieps, Lena Kitsopoulou, Panos Koronis, Maria Votti | F121: Italy, Brazil, Greece | G121: August 13, 2021 | H121: 2021 | I121: 2021 | J121: =YEAR(TODAY())-Table1[[#This Row],[Release_year]] -> 5 | K121: TV-MA | L121: =_xlfn.XLOOKUP(Table1[[#This Row],[Rating]],Ratings!A$2:A$15,Ratings!B$2:B$15) -> Adult | M121: =_xlfn.XLOOKUP(Table1[[#This Row],[Rating Category]],Recommendation!A$2:A$6,Recommendation!B$2:B$6) -> Restricted | N121: 110 | O121: {=_xlfn.IFS(Table1[[#This Row],[Duration]]<90,"Short",Table1[[#This Row],[Duration]]<180,"Medium",Table1[[#This Row],[Duration]]<=240,"Long",TRUE,"Seasons")} -> Medium | P121: Action & Adventure
A122: s274 | B122: TV Show | C122: Gone for Good | D122: Juan Carlos Medina | E122: Finnegan Oldfield, Nicolas Duvauchelle, Guillaume Gouix, Garance Marillier, Nailia Harzoune | F122: France | G122: August 13, 2021 | H122: 2021 | I122: 2021 | J122: =YEAR(TODAY())-Table1[[#This Row],[Release_year]] -> 5 | K122: TV-MA | L122: =_xlfn.XLOOKUP(Table1[[#This Row],[Rating]],Ratings!A$2:A$15,Ratings!B$2:B$15) -> Adult | M122: =_xlfn.XLOOKUP(Table1[[#This Row],[Rating Category]],Recommendation!A$2:A$6,Recommendation!B$2:B$6) -> Restricted | N122: 1 Season | O122: {=_xlfn.IFS(Table1[[#This Row],[Duration]]<90,"Short",Table1[[#This Row],[Duration]]<180,"Medium",Table1[[#This Row],[Duration]]<=240,"Long",TRUE,"Seasons")} -> Seasons | P122: Crime TV Shows, International TV Shows, TV Dramas
A123: s277 | B123: TV Show | C123: Valeria | D123: Inma Torrente | E123: Diana Gmez, Silma Lpez, Paula Malia, Teresa Riott, Maxi Iglesias, Ibrahim Al Shami | F123: Spain | G123: August 13, 2021 | H123: 2021 | I123: 2021 | J123: =YEAR(TODAY())-Table1[[#This Row],[Release_year]] -> 5 | K123: TV-MA | L123: =_xlfn.XLOOKUP(Table1[[#This Row],[Rating]],Ratings!A$2:A$15,Ratings!B$2:B$15) -> Adult | M123: =_xlfn.XLOOKUP(Table1[[#This Row],[Rating Category]],Recommendation!A$2:A$6,Recommendation!B$2:B$6) -> Restricted | N123: 2 Seasons | O123: {=_xlfn.IFS(Table1[[#This Row],[Duration]]<90,"Short",Table1[[#This Row],[Duration]]<180,"Medium",Table1[[#This Row],[Duration]]<=240,"Long",TRUE,"Seasons")} -> Seasons | P123: International TV Shows, Romantic TV Shows, Spanish-Language TV Shows
A124: s279 | B124: Movie | C124: Lokillo: Nothing's the Same | D124: Julin Gaviria | E124: Lokillo Florez | F124: Colombia | G124: August 12, 2021 | H124: 2021 | I124: 2021 | J124: =YEAR(TODAY())-Table1[[#This Row],[Release_year]] -> 5 | K124: TV-MA | L124: =_xlfn.XLOOKUP(Table1[[#This Row],[Rating]],Ratings!A$2:A$15,Ratings!B$2:B$15) -> Adult | M124: =_xlfn.XLOOKUP(Table1[[#This Row],[Rating Category]],Recommendation!A$2:A$6,Recommendation!B$2:B$6) -> Restricted | N124: 64 | O124: {=_xlfn.IFS(Table1[[#This Row],[Duration]]<90,"Short",Table1[[#This Row],[Duration]]<180,"Medium",Table1[[#This Row],[Duration]]<=240,"Long",TRUE,"Seasons")} -> Short | P124: Stand-Up Comedy
A125: s280 | B125: Movie | C125: Monster Hunter: Legends of the Guild | D125: Steven Yamamoto | E125: Ben Rausch, Erica Lindbeck, Dante Basco, Brando Eaton, Stephen Kramer Glickman, Caroline Caliston, G.K. Bowes, Dan McCoy | F125: United States, Japan | G125: August 12, 2021 | H125: 2021 | I125: 2021 | J125: =YEAR(TODAY())-Table1[[#This Row],[Release_year]] -> 5 | K125: TV-PG | L125: =_xlfn.XLOOKUP(Table1[[#This Row],[Rating]],Ratings!A$2:A$15,Ratings!B$2:B$15) -> Family | M125: =_xlfn.XLOOKUP(Table1[[#This Row],[Rating Category]],Recommendation!A$2:A$6,Recommendation!B$2:B$6) -> Guidance | N125: 59 | O125: {=_xlfn.IFS(Table1[[#This Row],[Duration]]<90,"Short",Table1[[#This Row],[Duration]]<180,"Medium",Table1[[#This Row],[Duration]]<=240,"Long",TRUE,"Seasons")} -> Short | P125: Action & Adventure, Anime Features, Children & Family Movies
A126: s282 | B126: Movie | C126: Brother Jekwu | D126: Charles Uwagbai | E126: Mike Ezuruonye, Juliet Ochienge, Angela Okorie, Huddah Monroe, Catherine Kamau, Naomi Mburu, Derrick Aduwo, Chris Kamau, Abubakar Salum, Celebrity Landlord | F126: Nigeria | G126: August 11, 2021 | H126: 2021 | I126: 2016 | J126: =YEAR(TODAY())-Table1[[#This Row],[Release_year]] -> 10 | K126: TV-14 | L126: =_xlfn.XLOOKUP(Table1[[#This Row],[Rating]],Ratings!A$2:A$15,Ratings!B$2:B$15) -> Teen | M126: =_xlfn.XLOOKUP(Table1[[#This Row],[Rating Category]],Recommendation!A$2:A$6,Recommendation!B$2:B$6) -> Guidance | N126: 101 | O126: {=_xlfn.IFS(Table1[[#This Row],[Duration]]<90,"Short",Table1[[#This Row],[Duration]]<180,"Medium",Table1[[#This Row],[Duration]]<=240,"Long",TRUE,"Seasons")} -> Medium | P126: Comedies, International Movies
A127: s283 | B127: Movie | C127: La diosa del asfalto | D127: Julin Hernndez | E127: Ximena Romo, Mabel Cadena, Alejandra Herrera, Nelly Gonzlez, Samantha Orozco, Axel Arenas, Esteban Caicedo, Paulina Goto, Raquel Robles, Baby Btiz, Pascacio Lpez, Jun Carlos Torres, Javier Olivn, Claudia Lobo, Giovanna Zacaras | F127: Mexico | G127: August 11, 2021 | H127: 2021 | I127: 2020 | J127: =YEAR(TODAY())-Table1[[#This Row],[Release_year]] -> 6 | K127: TV-MA | L127: =_xlfn.XLOOKUP(Table1[[#This Row],[Rating]],Ratings!A$2:A$15,Ratings!B$2:B$15) -> Adult | M127: =_xlfn.XLOOKUP(Table1[[#This Row],[Rating Category]],Recommendation!A$2:A$6,Recommendation!B$2:B$6) -> Restricted | N127: 127 | O127: {=_xlfn.IFS(Table1[[#This Row],[Duration]]<90,"Short",Table1[[#This Row],[Duration]]<180,"Medium",Table1[[#This Row],[Duration]]<=240,"Long",TRUE,"Seasons")} -> Medium | P127: Dramas, Independent Movies, International Movies
A128: s285 | B128: Movie | C128: The Kissing Booth 3 | D128: Vince Marcello | E128: Joey King, Joel Courtney, Jacob Elordi, Molly Ringwald, Taylor Zakhar Perez, Maisie Richardson-Sellers, Meganne Young, Stephen Jennings | F128: United Kingdom, United States | G128: August 11, 2021 | H128: 2021 | I128: 2021 | J128: =YEAR(TODAY())-Table1[[#This Row],[Release_year]] -> 5 | K128: TV-14 | L128: =_xlfn.XLOOKUP(Table1[[#This Row],[Rating]],Ratings!A$2:A$15,Ratings!B$2:B$15) -> Teen | M128: =_xlfn.XLOOKUP(Table1[[#This Row],[Rating Category]],Recommendation!A$2:A$6,Recommendation!B$2:B$6) -> Guidance | N128: 114 | O128: {=_xlfn.IFS(Table1[[#This Row],[Duration]]<90,"Short",Table1[[#This Row],[Duration]]<180,"Medium",Table1[[#This Row],[Duration]]<=240,"Long",TRUE,"Seasons")} -> Medium | P128: Comedies, Romantic Movies
A129: s286 | B129: Movie | C129: The Railway Man | D129: Jonathan Teplitzky | E129: Colin Firth, Nicole Kidman, Jeremy Irvine, Stellan Skarsgrd, Sam Reid, Hiroyuki Sanada, Michael MacKenzie, Tom Stokes | F129: Switzerland, United Kingdom, Australia | G129: August 11, 2021 | H129: 2021 | I129: 2013 | J129: =YEAR(TODAY())-Table1[[#This Row],[Release_year]] -> 13 | K129: R | L129: =_xlfn.XLOOKUP(Table1[[#This Row],[Rating]],Ratings!A$2:A$15,Ratings!B$2:B$15) -> Adult | M129: =_xlfn.XLOOKUP(Table1[[#This Row],[Rating Category]],Recommendation!A$2:A$6,Recommendation!B$2:B$6) -> Restricted | N129: 108 | O129: {=_xlfn.IFS(Table1[[#This Row],[Duration]]<90,"Short",Table1[[#This Row],[Duration]]<180,"Medium",Table1[[#This Row],[Duration]]<=240,"Long",TRUE,"Seasons")} -> Medium | P129: Dramas, International Movies
A130: s293 | B130: Movie | C130: Quartet | D130: Dustin Hoffman | E130: Maggie Smith, Tom Courtenay, Billy Connolly, Pauline Collins, Michael Gambon, Andrew Sachs, Sheridan Smith, David Ryall, Trevor Peacock, Gwyneth Jones | F130: United Kingdom | G130: August 8, 2021 | H130: 2021 | I130: 2012 | J130: =YEAR(TODAY())-Table1[[#This Row],[Release_year]] -> 14 | K130: PG-13 | L130: =_xlfn.XLOOKUP(Table1[[#This Row],[Rating]],Ratings!A$2:A$15,Ratings!B$2:B$15) -> Teen | M130: =_xlfn.XLOOKUP(Table1[[#This Row],[Rating Category]],Recommendation!A$2:A$6,Recommendation!B$2:B$6) -> Guidance | N130: 98 | O130: {=_xlfn.IFS(Table1[[#This Row],[Duration]]<90,"Short",Table1[[#This Row],[Duration]]<180,"Medium",Table1[[#This Row],[Duration]]<=240,"Long",TRUE,"Seasons")} -> Medium | P130: Comedies, Dramas, Independent Movies
A131: s294 | B131: Movie | C131: Slay | D131: Adze Ugah | E131: Enhle Mbali, Ramsey Nouah, Dawn Thandeka Kang, Idris Sultan, Tumi Morake, Trevor Gumbi, Lillian Dube, Kaly Bossy Asante, Shaleen Surtie, Fabian Lojege | F131: South Africa | G131: August 8, 2021 | H131: 2021 | I131: 2021 | J131: =YEAR(TODAY())-Table1[[#This Row],[Release_year]] -> 5 | K131: TV-MA | L131: =_xlfn.XLOOKUP(Table1[[#This Row],[Rating]],Ratings!A$2:A$15,Ratings!B$2:B$15) -> Adult | M131: =_xlfn.XLOOKUP(Table1[[#This Row],[Rating Category]],Recommendation!A$2:A$6,Recommendation!B$2:B$6) -> Restricted | N131: 86 | O131: {=_xlfn.IFS(Table1[[#This Row],[Duration]]<90,"Short",Table1[[#This Row],[Duration]]<180,"Medium",Table1[[#This Row],[Duration]]<=240,"Long",TRUE,"Seasons")} -> Short | P131: Comedies, International Movies, Romantic Movies
A132: s296 | B132: Movie | C132: The Paper Tigers | D132: Quoc Bao Tran | E132: Alain Uy, Ron Yuan, Mykel Shannon Jenkins, Jae Suh Park, Matthew Page, Joziah Lagonoy, Raymond Ma | F132: United States | G132: August 7, 2021 | H132: 2021 | I132: 2021 | J132: =YEAR(TODAY())-Table1[[#This Row],[Release_year]] -> 5 | K132: PG-13 | L132: =_xlfn.XLOOKUP(Table1[[#This Row],[Rating]],Ratings!A$2:A$15,Ratings!B$2:B$15) -> Teen | M132: =_xlfn.XLOOKUP(Table1[[#This Row],[Rating Category]],Recommendation!A$2:A$6,Recommendation!B$2:B$6) -> Guidance | N132: 111 | O132: {=_xlfn.IFS(Table1[[#This Row],[Duration]]<90,"Short",Table1[[#This Row],[Duration]]<180,"Medium",Table1[[#This Row],[Duration]]<=240,"Long",TRUE,"Seasons")} -> Medium | P132: Action & Adventure, Comedies
A133: s298 | B133: TV Show | C133: Navarasa | D133: Bejoy Nambiar, Priyadarshan, Karthik Narain, Vasanth Sai, Karthik Subbaraj, Arvind Swamy, Rathindran R Prasad, Sarjun, Gautham Vasudev Menon | E133: Suriya, Vijay Sethupathi, Revathy, Prakash Raj, Siddarth, Parvathy, Delhi Ganesh, Gautham Vasudev Menon, Anjali, Yogi Babu, Aditi Balan, Remya Nambeesan, Poorna, Prayaga Martin, Rythvika Suriya, Arvind Swamy, Prasanna, Atharva, Bobby Simha, Ashok Selvan, Nedumudi Venu, Kishore | F133: India | G133: August 6, 2021 | H133: 2021 | I133: 2021 | J133: =YEAR(TODAY())-Table1[[#This Row],[Release_year]] -> 5 | K133: TV-MA | L133: =_xlfn.XLOOKUP(Table1[[#This Row],[Rating]],Ratings!A$2:A$15,Ratings!B$2:B$15) -> Adult | M133: =_xlfn.XLOOKUP(Table1[[#This Row],[Rating Category]],Recommendation!A$2:A$6,Recommendation!B$2:B$6) -> Restricted | N133: 1 Season | O133: {=_xlfn.IFS(Table1[[#This Row],[Duration]]<90,"Short",Table1[[#This Row],[Duration]]<180,"Medium",Table1[[#This Row],[Duration]]<=240,"Long",TRUE,"Seasons")} -> Seasons | P133: TV Shows
A134: s299 | B134: Movie | C134: Quam's Money | D134: Kayode Kasum | E134: Falz, Nse Ikpe-Etim, Williams Uchemba, Toni Tones, Michelle Dede, Karibi Fubara, Buchi Ojei, Jemima Osunde, Blossom Chukwujekwu, Gbubemi Ejeye, Badmus Olakunle | F134: Nigeria | G134: August 6, 2021 | H134: 2021 | I134: 2020 | J134: =YEAR(TODAY())-Table1[[#This Row],[Release_year]] -> 6 | K134: TV-MA | L134: =_xlfn.XLOOKUP(Table1[[#This Row],[Rating]],Ratings!A$2:A$15,Ratings!B$2:B$15) -> Adult | M134: =_xlfn.XLOOKUP(Table1[[#This Row],[Rating Category]],Recommendation!A$2:A$6,Recommendation!B$2:B$6) -> Restricted | N134: 115 | O134: {=_xlfn.IFS(Table1[[#This Row],[Duration]]<90,"Short",Table1[[#This Row],[Duration]]<180,"Medium",Table1[[#This Row],[Duration]]<=240,"Long",TRUE,"Seasons")} -> Medium | P134: Comedies, Dramas, International Movies
A135: s300 | B135: Movie | C135: The Swarm | D135: Just Philippot | E135: Suliane Brahim, Sofian Khammes, Marie Narbonne, Raphal Romand, Stphan Castang, Victor Bonnel, Christian Bouillette, Renan Prvot, Vincent Deniard | F135: France | G135: August 6, 2021 | H135: 2021 | I135: 2021 | J135: =YEAR(TODAY())-Table1[[#This Row],[Release_year]] -> 5 | K135: TV-14 | L135: =_xlfn.XLOOKUP(Table1[[#This Row],[Rating]],Ratings!A$2:A$15,Ratings!B$2:B$15) -> Teen | M135: =_xlfn.XLOOKUP(Table1[[#This Row],[Rating Category]],Recommendation!A$2:A$6,Recommendation!B$2:B$6) -> Guidance | N135: 102 | O135: {=_xlfn.IFS(Table1[[#This Row],[Duration]]<90,"Short",Table1[[#This Row],[Duration]]<180,"Medium",Table1[[#This Row],[Duration]]<=240,"Long",TRUE,"Seasons")} -> Medium | P135: Horror Movies, Independent Movies, International Movies
A136: s301 | B136: Movie | C136: Vivo | D136: Kirk DeMicco, Brandon Jeffords | E136: Lin-Manuel Miranda, Ynairaly Simo, Zoe Saldana, Juan de Marcos, Brian Tyree Henry, Gloria Estefan, Michael Rooker, Nicole Byer | F136: Canada, United States | G136: August 6, 2021 | H136: 2021 | I136: 2021 | J136: =YEAR(TODAY())-Table1[[#This Row],[Release_year]] -> 5 | K136: PG | L136: =_xlfn.XLOOKUP(Table1[[#This Row],[Rating]],Ratings!A$2:A$15,Ratings!B$2:B$15) -> Family | M136: =_xlfn.XLOOKUP(Table1[[#This Row],[Rating Category]],Recommendation!A$2:A$6,Recommendation!B$2:B$6) -> Guidance | N136: 100 | O136: {=_xlfn.IFS(Table1[[#This Row],[Duration]]<90,"Short",Table1[[#This Row],[Duration]]<180,"Medium",Table1[[#This Row],[Duration]]<=240,"Long",TRUE,"Seasons")} -> Medium | P136: Children & Family Movies, Music & Musicals
A137: s302 | B137: Movie | C137: Chennai Express | D137: Rohit Shetty | E137: Shah Rukh Khan, Deepika Padukone, Nikitin Dheer, Satyaraj, Kamini Kaushal, Lekh Tandon, Mukesh Tiwari | F137: India | G137: August 5, 2021 | H137: 2021 | I137: 2013 | J137: =YEAR(TODAY())-Table1[[#This Row],[Release_year]] -> 13 | K137: TV-14 | L137: =_xlfn.XLOOKUP(Table1[[#This Row],[Rating]],Ratings!A$2:A$15,Ratings!B$2:B$15) -> Teen | M137: =_xlfn.XLOOKUP(Table1[[#This Row],[Rating Category]],Recommendation!A$2:A$6,Recommendation!B$2:B$6) -> Guidance | N137: 135 | O137: {=_xlfn.IFS(Table1[[#This Row],[Duration]]<90,"Short",Table1[[#This Row],[Duration]]<180,"Medium",Table1[[#This Row],[Duration]]<=240,"Long",TRUE,"Seasons")} -> Medium | P137: Action & Adventure, Comedies, International Movies
A138: s304 | B138: Movie | C138: Esperando la carroza | D138: Alejandro Doria | E138: Luis Brandoni, China Zorrilla, Antonio Gasalla, Julio De Grazia, Betiana Blum, Monica Villa, Juan Manuel Tenuta, Andrea Tenuta, Cecilia Rossetto, Enrique Pinti | F138: Argentina | G138: August 5, 2021 | H138: 2021 | I138: 1985 | J138: =YEAR(TODAY())-Table1[[#This Row],[Release_year]] -> 41 | K138: TV-MA | L138: =_xlfn.XLOOKUP(Table1[[#This Row],[Rating]],Ratings!A$2:A$15,Ratings!B$2:B$15) -> Adult | M138: =_xlfn.XLOOKUP(Table1[[#This Row],[Rating Category]],Recommendation!A$2:A$6,Recommendation!B$2:B$6) -> Restricted | N138: 95 | O138: {=_xlfn.IFS(Table1[[#This Row],[Duration]]<90,"Short",Table1[[#This Row],[Duration]]<180,"Medium",Table1[[#This Row],[Duration]]<=240,"Long",TRUE,"Seasons")} -> Medium | P138: Comedies, Cult Movies, International Movies
A139: s305 | B139: Movie | C139: Lady Boss: The Jackie Collins Story | D139: Laura Fairrie | E139: Jackie Collins | F139: United Kingdom | G139: August 5, 2021 | H139: 2021 | I139: 2021 | J139: =YEAR(TODAY())-Table1[[#This Row],[Release_year]] -> 5 | K139: TV-14 | L139: =_xlfn.XLOOKUP(Table1[[#This Row],[Rating]],Ratings!A$2:A$15,Ratings!B$2:B$15) -> Teen | M139: =_xlfn.XLOOKUP(Table1[[#This Row],[Rating Category]],Recommendation!A$2:A$6,Recommendation!B$2:B$6) -> Guidance | N139: 97 | O139: {=_xlfn.IFS(Table1[[#This Row],[Duration]]<90,"Short",Table1[[#This Row],[Duration]]<180,"Medium",Table1[[#This Row],[Duration]]<=240,"Long",TRUE,"Seasons")} -> Medium | P139: Documentaries
A140: s306 | B140: Movie | C140: Tango Feroz | D140: Marcelo Pieyro | E140: Fernn Mirs, Cecilia Dopazo, Imanol Arias, Hctor Alterio, Leonardo Sbaraglia, Federico D'Ela, David Masajnik, Cristina Banegas, Ernesto Alterio, Antonio Birabent | F140: Argentina, Spain | G140: August 5, 2021 | H140: 2021 | I140: 1993 | J140: =YEAR(TODAY())-Table1[[#This Row],[Release_year]] -> 33 | K140: TV-MA | L140: =_xlfn.XLOOKUP(Table1[[#This Row],[Rating]],Ratings!A$2:A$15,Ratings!B$2:B$15) -> Adult | M140: =_xlfn.XLOOKUP(Table1[[#This Row],[Rating Category]],Recommendation!A$2:A$6,Recommendation!B$2:B$6) -> Restricted | N140: 124 | O140: {=_xlfn.IFS(Table1[[#This Row],[Duration]]<90,"Short",Table1[[#This Row],[Duration]]<180,"Medium",Table1[[#This Row],[Duration]]<=240,"Long",TRUE,"Seasons")} -> Medium | P140: Classic Movies, Dramas, International Movies
A141: s307 | B141: Movie | C141: '76 | D141: Izu Ojukwu | E141: Ramsey Nouah, Rita Dominic, Chidi Mokeme, Ibinabo Fiberesima, Daniel K. Daniel, Memry Savanhu, Adonijah Owiriwa, Pat Nebo, Nelly Ekwereogu, Shuaibu Ebenesi Adams, Debo Oguns, Ben Nwosu, Ada Ofoegbu | F141: Nigeria | G141: August 4, 2021 | H141: 2021 | I141: 2016 | J141: =YEAR(TODAY())-Table1[[#This Row],[Release_year]] -> 10 | K141: TV-PG | L141: =_xlfn.XLOOKUP(Table1[[#This Row],[Rating]],Ratings!A$2:A$15,Ratings!B$2:B$15) -> Family | M141: =_xlfn.XLOOKUP(Table1[[#This Row],[Rating Category]],Recommendation!A$2:A$6,Recommendation!B$2:B$6) -> Guidance | N141: 118 | O141: {=_xlfn.IFS(Table1[[#This Row],[Duration]]<90,"Short",Table1[[#This Row],[Duration]]<180,"Medium",Table1[[#This Row],[Duration]]<=240,"Long",TRUE,"Seasons")} -> Medium | P141: Dramas, International Movies
A142: s308 | B142: Movie | C142: Aftermath | D142: Peter Winther | E142: Ashley Greene, Shawn Ashmore, Sharif Atkins, Britt Baron, Diana Hopper, Ross McCall, Jamie Kaler, Travis Coles, Susan Walters, Jason Liles | F142: United States | G142: August 4, 2021 | H142: 2021 | I142: 2021 | J142: =YEAR(TODAY())-Table1[[#This Row],[Release_year]] -> 5 | K142: TV-MA | L142: =_xlfn.XLOOKUP(Table1[[#This Row],[Rating]],Ratings!A$2:A$15,Ratings!B$2:B$15) -> Adult | M142: =_xlfn.XLOOKUP(Table1[[#This Row],[Rating Category]],Recommendation!A$2:A$6,Recommendation!B$2:B$6) -> Restricted | N142: 115 | O142: {=_xlfn.IFS(Table1[[#This Row],[Duration]]<90,"Short",Table1[[#This Row],[Duration]]<180,"Medium",Table1[[#This Row],[Duration]]<=240,"Long",TRUE,"Seasons")} -> Medium | P142: Horror Movies
A143: s309 | B143: Movie | C143: American Masters: Inventing David Geffen | D143: Susan Lacy | E143: David Geffen | F143: United States | G143: August 4, 2021 | H143: 2021 | I143: 2012 | J143: =YEAR(TODAY())-Table1[[#This Row],[Release_year]] -> 14 | K143: TV-MA | L143: =_xlfn.XLOOKUP(Table1[[#This Row],[Rating]],Ratings!A$2:A$15,Ratings!B$2:B$15) -> Adult | M143: =_xlfn.XLOOKUP(Table1[[#This Row],[Rating Category]],Recommendation!A$2:A$6,Recommendation!B$2:B$6) -> Restricted | N143: 115 | O143: {=_xlfn.IFS(Table1[[#This Row],[Duration]]<90,"Short",Table1[[#This Row],[Duration]]<180,"Medium",Table1[[#This Row],[Duration]]<=240,"Long",TRUE,"Seasons")} -> Medium | P143: Movies
A144: s315 | B144: Movie | C144: Heavy | D144: James Mangold | E144: Pruitt Taylor Vince, Shelley Winters, Liv Tyler, Debbie Harry, Evan Dando, Joe Grifasi, David Patrick Kelly, Marian Quinn | F144: United States | G144: August 3, 2021 | H144: 2021 | I144: 1995 | J144: =YEAR(TODAY())-Table1[[#This Row],[Release_year]] -> 31 | K144: R | L144: =_xlfn.XLOOKUP(Table1[[#This Row],[Rating]],Ratings!A$2:A$15,Ratings!B$2:B$15) -> Adult | M144: =_xlfn.XLOOKUP(Table1[[#This Row],[Rating Category]],Recommendation!A$2:A$6,Recommendation!B$2:B$6) -> Restricted | N144: 104 | O144: {=_xlfn.IFS(Table1[[#This Row],[Duration]]<90,"Short",Table1[[#This Row],[Duration]]<180,"Medium",Table1[[#This Row],[Duration]]<=240,"Long",TRUE,"Seasons")} -> Medium | P144: Dramas, Independent Movies, Romantic Movies
A145: s316 | B145: Movie | C145: Ije: The Journey | D145: Chineze Anyaene | E145: Genevieve Nnaji, Omotola Jalade-Ekeinde, Odalys Garcia, Ulrich Que, Jeff Swarthout, Clem Ohameze, Ann D. Carey, Anahit Setian, Danielle Soibelman, Jon Morgan Woodward | F145: United States, Nigeria | G145: August 3, 2021 | H145: 2021 | I145: 2010 | J145: =YEAR(TODAY())-Table1[[#This Row],[Release_year]] -> 16 | K145: TV-MA | L145: =_xlfn.XLOOKUP(Table1[[#This Row],[Rating]],Ratings!A$2:A$15,Ratings!B$2:B$15) -> Adult | M145: =_xlfn.XLOOKUP(Table1[[#This Row],[Rating Category]],Recommendation!A$2:A$6,Recommendation!B$2:B$6) -> Restricted | N145: 106 | O145: {=_xlfn.IFS(Table1[[#This Row],[Duration]]<90,"Short",Table1[[#This Row],[Duration]]<180,"Medium",Table1[[#This Row],[Duration]]<=240,"Long",TRUE,"Seasons")} -> Medium | P145: Dramas, International Movies
A146: s317 | B146: TV Show | C146: Office Girls | D146: Hsu Fu-chun | E146: Roy Chiu, Alice Ko, Tia Lee, Patrick Lee, Kuo Shu-yao, James Wen, Janel Tsai | F146: Taiwan | G146: August 3, 2021 | H146: 2021 | I146: 2011 | J146: =YEAR(TODAY())-Table1[[#This Row],[Release_year]] -> 15 | K146: TV-14 | L146: =_xlfn.XLOOKUP(Table1[[#This Row],[Rating]],Ratings!A$2:A$15,Ratings!B$2:B$15) -> Teen | M146: =_xlfn.XLOOKUP(Table1[[#This Row],[Rating Category]],Recommendation!A$2:A$6,Recommendation!B$2:B$6) -> Guidance | N146: 1 Season | O146: {=_xlfn.IFS(Table1[[#This Row],[Duration]]<90,"Short",Table1[[#This Row],[Duration]]<180,"Medium",Table1[[#This Row],[Duration]]<=240,"Long",TRUE,"Seasons")} -> Seasons | P146: International TV Shows, Romantic TV Shows, TV Comedies
A147: s326 | B147: Movie | C147: Beethoven | D147: Brian Levant | E147: Charles Grodin, Bonnie Hunt, Dean Jones, Oliver Platt, Stanley Tucci, Nicholle Tom, Christopher Castile, Sarah Rose Karr, David Duchovny, Patricia Heaton, O-Lan Jones, Nancy Fish | F147: United States | G147: August 1, 2021 | H147: 2021 | I147: 1992 | J147: =YEAR(TODAY())-Table1[[#This Row],[Release_year]] -> 34 | K147: PG | L147: =_xlfn.XLOOKUP(Table1[[#This Row],[Rating]],Ratings!A$2:A$15,Ratings!B$2:B$15) -> Family | M147: =_xlfn.XLOOKUP(Table1[[#This Row],[Rating Category]],Recommendation!A$2:A$6,Recommendation!B$2:B$6) -> Guidance | N147: 87 | O147: {=_xlfn.IFS(Table1[[#This Row],[Duration]]<90,"Short",Table1[[#This Row],[Duration]]<180,"Medium",Table1[[#This Row],[Duration]]<=240,"Long",TRUE,"Seasons")} -> Short | P147: Children & Family Movies, Comedies
A148: s327 | B148: Movie | C148: Beethoven's 2nd | D148: Rod Daniel | E148: Charles Grodin, Bonnie Hunt, Nicholle Tom, Christopher Castile, Sarah Rose Karr, Debi Mazar, Chris Penn | F148: United States | G148: August 1, 2021 | H148: 2021 | I148: 1993 | J148: =YEAR(TODAY())-Table1[[#This Row],[Release_year]] -> 33 | K148: PG | L148: =_xlfn.XLOOKUP(Table1[[#This Row],[Rating]],Ratings!A$2:A$15,Ratings!B$2:B$15) -> Family | M148: =_xlfn.XLOOKUP(Table1[[#This Row],[Rating Category]],Recommendation!A$2:A$6,Recommendation!B$2:B$6) -> Guidance | N148: 88 | O148: {=_xlfn.IFS(Table1[[#This Row],[Duration]]<90,"Short",Table1[[#This Row],[Duration]]<180,"Medium",Table1[[#This Row],[Duration]]<=240,"Long",TRUE,"Seasons")} -> Short | P148: Children & Family Movies, Comedies
A149: s328 | B149: Movie | C149: Beowulf | D149: Robert Zemeckis | E149: Ray Winstone, Anthony Hopkins, John Malkovich, Angelina Jolie, Robin Wright, Brendan Gleeson, Crispin Glover, Alison Lohman, Sharisse Baker-Bernard | F149: United States, United Kingdom | G149: August 1, 2021 | H149: 2021 | I149: 2007 | J149: =YEAR(TODAY())-Table1[[#This Row],[Release_year]] -> 19 | K149: PG-13 | L149: =_xlfn.XLOOKUP(Table1[[#This Row],[Rating]],Ratings!A$2:A$15,Ratings!B$2:B$15) -> Teen | M149: =_xlfn.XLOOKUP(Table1[[#This Row],[Rating Category]],Recommendation!A$2:A$6,Recommendation!B$2:B$6) -> Guidance | N149: 114 | O149: {=_xlfn.IFS(Table1[[#This Row],[Duration]]<90,"Short",Table1[[#This Row],[Duration]]<180,"Medium",Table1[[#This Row],[Duration]]<=240,"Long",TRUE,"Seasons")} -> Medium | P149: Action & Adventure, Sci-Fi & Fantasy
A150: s329 | B150: Movie | C150: Boyka: Undisputed | D150: Todor Chapkanov | E150: Scott Adkins, Teodora Duhovnikova, Alon Aboutboul, Julian Vergov, Brahim Achabbakhe, Paul Chahidi, Petio Petkov, Valentin Ganev, Vlado Mihailov | F150: Bulgaria, United States | G150: August 1, 2021 | H150: 2021 | I150: 2016 | J150: =YEAR(TODAY())-Table1[[#This Row],[Release_year]] -> 10 | K150: R | L150: =_xlfn.XLOOKUP(Table1[[#This Row],[Rating]],Ratings!A$2:A$15,Ratings!B$2:B$15) -> Adult | M150: =_xlfn.XLOOKUP(Table1[[#This Row],[Rating Category]],Recommendation!A$2:A$6,Recommendation!B$2:B$6) -> Restricted | N150: 90 | O150: {=_xlfn.IFS(Table1[[#This Row],[Duration]]<90,"Short",Table1[[#This Row],[Duration]]<180,"Medium",Table1[[#This Row],[Duration]]<=240,"Long",TRUE,"Seasons")} -> Medium | P150: Action & Adventure
A151: s330 | B151: Movie | C151: Catch Me If You Can | D151: Steven Spielberg | E151: Leonardo DiCaprio, Tom Hanks, Christopher Walken, Martin Sheen, Nathalie Baye, Amy Adams, James Brolin, Brian Howe, Frank John Hughes, Steve Eastin | F151: United States, Canada | G151: August 1, 2021 | H151: 2021 | I151: 2002 | J151: =YEAR(TODAY())-Table1[[#This Row],[Release_year]] -> 24 | K151: PG-13 | L151: =_xlfn.XLOOKUP(Table1[[#This Row],[Rating]],Ratings!A$2:A$15,Ratings!B$2:B$15) -> Teen | M151: =_xlfn.XLOOKUP(Table1[[#This Row],[Rating Category]],Recommendation!A$2:A$6,Recommendation!B$2:B$6) -> Guidance | N151: 142 | O151: {=_xlfn.IFS(Table1[[#This Row],[Duration]]<90,"Short",Table1[[#This Row],[Duration]]<180,"Medium",Table1[[#This Row],[Duration]]<=240,"Long",TRUE,"Seasons")} -> Medium | P151: Dramas
A152: s331 | B152: Movie | C152: Cloudy with a Chance of Meatballs | D152: Phil Lord, Christopher Miller | E152: Bill Hader, Anna Faris, James Caan, Andy Samberg, Bruce Campbell, Mr. T, Bobb'e J. Thompson, Benjamin Bratt, Neil Patrick Harris, Al Roker | F152: United States, Canada | G152: August 1, 2021 | H152: 2021 | I152: 2009 | J152: =YEAR(TODAY())-Table1[[#This Row],[Release_year]] -> 17 | K152: PG | L152: =_xlfn.XLOOKUP(Table1[[#This Row],[Rating]],Ratings!A$2:A$15,Ratings!B$2:B$15) -> Family | M152: =_xlfn.XLOOKUP(Table1[[#This Row],[Rating Category]],Recommendation!A$2:A$6,Recommendation!B$2:B$6) -> Guidance | N152: 90 | O152: {=_xlfn.IFS(Table1[[#This Row],[Duration]]<90,"Short",Table1[[#This Row],[Duration]]<180,"Medium",Table1[[#This Row],[Duration]]<=240,"Long",TRUE,"Seasons")} -> Medium | P152: Children & Family Movies, Comedies, Sci-Fi & Fantasy
A153: s333 | B153: Movie | C153: Deep Blue Sea | D153: Renny Harlin | E153: Thomas Jane, Saffron Burrows, Samuel L. Jackson, Jacqueline McKenzie, Michael Rapaport, Stellan Skarsgrd, LL Cool J, Aida Turturro, Cristos, Daniel Rey | F153: United States, Mexico | G153: August 1, 2021 | H153: 2021 | I153: 1999 | J153: =YEAR(TODAY())-Table1[[#This Row],[Release_year]] -> 27 | K153: R | L153: =_xlfn.XLOOKUP(Table1[[#This Row],[Rating]],Ratings!A$2:A$15,Ratings!B$2:B$15) -> Adult | M153: =_xlfn.XLOOKUP(Table1[[#This Row],[Rating Category]],Recommendation!A$2:A$6,Recommendation!B$2:B$6) -> Restricted | N153: 105 | O153: {=_xlfn.IFS(Table1[[#This Row],[Duration]]<90,"Short",Table1[[#This Row],[Duration]]<180,"Medium",Table1[[#This Row],[Duration]]<=240,"Long",TRUE,"Seasons")} -> Medium | P153: Action & Adventure, Horror Movies, Sci-Fi & Fantasy
A154: s334 | B154: Movie | C154: Ferris Bueller's Day Off | D154: John Hughes | E154: Matthew Broderick, Alan Ruck, Mia Sara, Jeffrey Jones, Jennifer Grey, Cindy Pickett, Lyman Ward, Edie McClurg, Charlie Sheen, Kristy Swanson, Ben Stein, Del Close | F154: United States | G154: August 1, 2021 | H154: 2021 | I154: 1986 | J154: =YEAR(TODAY())-Table1[[#This Row],[Release_year]] -> 40 | K154: PG-13 | L154: =_xlfn.XLOOKUP(Table1[[#This Row],[Rating]],Ratings!A$2:A$15,Ratings!B$2:B$15) -> Teen | M154: =_xlfn.XLOOKUP(Table1[[#This Row],[Rating Category]],Recommendation!A$2:A$6,Recommendation!B$2:B$6) -> Guidance | N154: 103 | O154: {=_xlfn.IFS(Table1[[#This Row],[Duration]]<90,"Short",Table1[[#This Row],[Duration]]<180,"Medium",Table1[[#This Row],[Duration]]<=240,"Long",TRUE,"Seasons")} -> Medium | P154: Classic Movies, Comedies, Cult Movies
A155: s335 | B155: Movie | C155: Five Feet Apart | D155: Justin Baldoni | E155: Haley Lu Richardson, Cole Sprouse, Moiss Arias, Kimberly Hbert Gregory, Parminder Nagra, Claire Forlani, Emily Baldoni, Gary Weeks, Cynthia Evans | F155: United States | G155: August 1, 2021 | H155: 2021 | I155: 2019 | J155: =YEAR(TODAY())-Table1[[#This Row],[Release_year]] -> 7 | K155: PG-13 | L155: =_xlfn.XLOOKUP(Table1[[#This Row],[Rating]],Ratings!A$2:A$15,Ratings!B$2:B$15) -> Teen | M155: =_xlfn.XLOOKUP(Table1[[#This Row],[Rating Category]],Recommendation!A$2:A$6,Recommendation!B$2:B$6) -> Guidance | N155: 116 | O155: {=_xlfn.IFS(Table1[[#This Row],[Duration]]<90,"Short",Table1[[#This Row],[Duration]]<180,"Medium",Table1[[#This Row],[Duration]]<=240,"Long",TRUE,"Seasons")} -> Medium | P155: Dramas, Romantic Movies
A156: s336 | B156: Movie | C156: Freedomland | D156: Joe Roth | E156: Samuel L. Jackson, Julianne Moore, Edie Falco, Ron Eldard, William Forsythe, Aunjanue Ellis, Anthony Mackie, LaTanya Richardson Jackson, Clarke Peters, Peter Friedman, Domenick Lombardozzi | F156: United States | G156: August 1, 2021 | H156: 2021 | I156: 2006 | J156: =YEAR(TODAY())-Table1[[#This Row],[Release_year]] -> 20 | K156: R | L156: =_xlfn.XLOOKUP(Table1[[#This Row],[Rating]],Ratings!A$2:A$15,Ratings!B$2:B$15) -> Adult | M156: =_xlfn.XLOOKUP(Table1[[#This Row],[Rating Category]],Recommendation!A$2:A$6,Recommendation!B$2:B$6) -> Restricted | N156: 113 | O156: {=_xlfn.IFS(Table1[[#This Row],[Duration]]<90,"Short",Table1[[#This Row],[Duration]]<180,"Medium",Table1[[#This Row],[Duration]]<=240,"Long",TRUE,"Seasons")} -> Medium | P156: Dramas, Thrillers
A157: s338 | B157: Movie | C157: Good Luck Chuck | D157: Mark Helfrich | E157: Dane Cook, Jessica Alba, Dan Fogler, Ellia English, Sasha Pieterse, Annie Wood, Lonny Ross, Chelan Simmons, Simone Bailly, Jodelle Ferland, Crystal Lowe, Troy Gentile, Georgia Craig, Michelle Harrison, Chiara Zanni | F157: United States, Canada | G157: August 1, 2021 | H157: 2021 | I157: 2007 | J157: =YEAR(TODAY())-Table1[[#This Row],[Release_year]] -> 19 | K157: R | L157: =_xlfn.XLOOKUP(Table1[[#This Row],[Rating]],Ratings!A$2:A$15,Ratings!B$2:B$15) -> Adult | M157: =_xlfn.XLOOKUP(Table1[[#This Row],[Rating Category]],Recommendation!A$2:A$6,Recommendation!B$2:B$6) -> Restricted | N157: 99 | O157: {=_xlfn.IFS(Table1[[#This Row],[Duration]]<90,"Short",Table1[[#This Row],[Duration]]<180,"Medium",Table1[[#This Row],[Duration]]<=240,"Long",TRUE,"Seasons")} -> Medium | P157: Comedies, Romantic Movies
A158: s341 | B158: Movie | C158: Inception | D158: Christopher Nolan | E158: Leonardo DiCaprio, Joseph Gordon-Levitt, Elliot Page, Tom Hardy, Ken Watanabe, Dileep Rao, Cillian Murphy, Tom Berenger, Marion Cotillard, Pete Postlethwaite, Michael Caine, Lukas Haas | F158: United States, United Kingdom | G158: August 1, 2021 | H158: 2021 | I158: 2010 | J158: =YEAR(TODAY())-Table1[[#This Row],[Release_year]] -> 16 | K158: PG-13 | L158: =_xlfn.XLOOKUP(Table1[[#This Row],[Rating]],Ratings!A$2:A$15,Ratings!B$2:B$15) -> Teen | M158: =_xlfn.XLOOKUP(Table1[[#This Row],[Rating Category]],Recommendation!A$2:A$6,Recommendation!B$2:B$6) -> Guidance | N158: 148 | O158: {=_xlfn.IFS(Table1[[#This Row],[Duration]]<90,"Short",Table1[[#This Row],[Duration]]<180,"Medium",Table1[[#This Row],[Duration]]<=240,"Long",TRUE,"Seasons")} -> Medium | P158: Action & Adventure, Sci-Fi & Fantasy, Thrillers
... A181: s378 | B181: Movie | C181: Bartkowiak | D181: Daniel Markowicz | E181: Jzef Pawowski, Zofia Domalik, Szymon Bobrowski, Bartomiej Topa, Janusz Chabior, Rafa Zawierucha, Antoni Pawlicki, Cezary ukaszewicz, Danuta Stenka, Jan Frycz, Damian Majewski | F181: Poland | G181: July 28, 2021 | H181: 2021 | I181: 2021 | J181: =YEAR(TODAY())-Table1[[#This Row],[Release_year]] -> 5 | K181: TV-MA | L181: =_xlfn.XLOOKUP(Table1[[#This Row],[Rating]],Ratings!A$2:A$15,Ratings!B$2:B$15) -> Adult | M181: =_xlfn.XLOOKUP(Table1[[#This Row],[Rating Category]],Recommendation!A$2:A$6,Recommendation!B$2:B$6) -> Restricted | N181: 92 | O181: {=_xlfn.IFS(Table1[[#This Row],[Duration]]<90,"Short",Table1[[#This Row],[Duration]]<180,"Medium",Table1[[#This Row],[Duration]]<=240,"Long",TRUE,"Seasons")} -> Medium | P181: Action & Adventure, International Movies
A182: s381 | B182: TV Show | C182: The Flash | D182: Glen Winter | E182: Grant Gustin, Candice Patton, Danielle Panabaker, Carlos Valdes, Tom Cavanagh, Jesse L. Martin, Neil Sandilands, Britne Oldford, Danielle Nicolet, Keiynan Lonsdale, Kim Engelbrecht | F182: United States | G182: July 28, 2021 | H182: 2021 | I182: 2021 | J182: =YEAR(TODAY())-Table1[[#This Row],[Release_year]] -> 5 | K182: TV-14 | L182: =_xlfn.XLOOKUP(Table1[[#This Row],[Rating]],Ratings!A$2:A$15,Ratings!B$2:B$15) -> Teen | M182: =_xlfn.XLOOKUP(Table1[[#This Row],[Rating Category]],Recommendation!A$2:A$6,Recommendation!B$2:B$6) -> Guidance | N182: 7 Seasons | O182: {=_xlfn.IFS(Table1[[#This Row],[Duration]]<90,"Short",Table1[[#This Row],[Duration]]<180,"Medium",Table1[[#This Row],[Duration]]<=240,"Long",TRUE,"Seasons")} -> Seasons | P182: Crime TV Shows, TV Action & Adventure, TV Sci-Fi & Fantasy
A183: s384 | B183: Movie | C183: Department | D183: Ram Gopal Varma | E183: Amitabh Bachchan, Sanjay Dutt, Rana Daggubati, Vijay Raaz, Abhimanyu Singh, Madhu Shalini, Deepak Tijori, Anjana Sukhani, Manchu Lakshmi | F183: India | G183: July 27, 2021 | H183: 2021 | I183: 2012 | J183: =YEAR(TODAY())-Table1[[#This Row],[Release_year]] -> 14 | K183: TV-MA | L183: =_xlfn.XLOOKUP(Table1[[#This Row],[Rating]],Ratings!A$2:A$15,Ratings!B$2:B$15) -> Adult | M183: =_xlfn.XLOOKUP(Table1[[#This Row],[Rating Category]],Recommendation!A$2:A$6,Recommendation!B$2:B$6) -> Restricted | N183: 143 | O183: {=_xlfn.IFS(Table1[[#This Row],[Duration]]<90,"Short",Table1[[#This Row],[Duration]]<180,"Medium",Table1[[#This Row],[Duration]]<=240,"Long",TRUE,"Seasons")} -> Medium | P183: Action & Adventure, International Movies
A184: s390 | B184: Movie | C184: The Operative | D184: Yuval Adler | E184: Diane Kruger, Martin Freeman, Cas Anvar, Rotem Keinan, Yohanan Herson | F184: France, Israel, Germany, United States, United Kingdom | G184: July 27, 2021 | H184: 2021 | I184: 2019 | J184: =YEAR(TODAY())-Table1[[#This Row],[Release_year]] -> 7 | K184: TV-MA | L184: =_xlfn.XLOOKUP(Table1[[#This Row],[Rating]],Ratings!A$2:A$15,Ratings!B$2:B$15) -> Adult | M184: =_xlfn.XLOOKUP(Table1[[#This Row],[Rating Category]],Recommendation!A$2:A$6,Recommendation!B$2:B$6) -> Restricted | N184: 117 | O184: {=_xlfn.IFS(Table1[[#This Row],[Duration]]<90,"Short",Table1[[#This Row],[Duration]]<180,"Medium",Table1[[#This Row],[Duration]]<=240,"Long",TRUE,"Seasons")} -> Medium | P184: Dramas, International Movies, Thrillers
A185: s393 | B185: Movie | C185: Django Unchained | D185: Quentin Tarantino | E185: Jamie Foxx, Christoph Waltz, Leonardo DiCaprio, Kerry Washington, Samuel L. Jackson, Walton Goggins, Dennis Christopher, James Remar, David Steen, Dana Gourrier, Nichole Galicia, Laura Cayouette, Ato Essandoh, Sammi Rotibi, Escalante Lundy, Don Johnson | F185: United States | G185: July 24, 2021 | H185: 2021 | I185: 2012 | J185: =YEAR(TODAY())-Table1[[#This Row],[Release_year]] -> 14 | K185: R | L185: =_xlfn.XLOOKUP(Table1[[#This Row],[Rating]],Ratings!A$2:A$15,Ratings!B$2:B$15) -> Adult | M185: =_xlfn.XLOOKUP(Table1[[#This Row],[Rating Category]],Recommendation!A$2:A$6,Recommendation!B$2:B$6) -> Restricted | N185: 165 | O185: {=_xlfn.IFS(Table1[[#This Row],[Duration]]<90,"Short",Table1[[#This Row],[Duration]]<180,"Medium",Table1[[#This Row],[Duration]]<=240,"Long",TRUE,"Seasons")} -> Medium | P185: Action & Adventure, Dramas
A186: s394 | B186: Movie | C186: A Second Chance: Rivals! | D186: Clay Glen | E186: Emily Morris, Stella Shute, Eva Grados, India Colombi, Nina Pearce, Adam Tuominen, Carmel Johnson, Natasha Wanganeen, Elysia Markou, Alexander Lloyd, Amy Handley | F186: Australia | G186: July 23, 2021 | H186: 2021 | I186: 2021 | J186: =YEAR(TODAY())-Table1[[#This Row],[Release_year]] -> 5 | K186: PG | L186: =_xlfn.XLOOKUP(Table1[[#This Row],[Rating]],Ratings!A$2:A$15,Ratings!B$2:B$15) -> Family | M186: =_xlfn.XLOOKUP(Table1[[#This Row],[Rating Category]],Recommendation!A$2:A$6,Recommendation!B$2:B$6) -> Guidance | N186: 91 | O186: {=_xlfn.IFS(Table1[[#This Row],[Duration]]<90,"Short",Table1[[#This Row],[Duration]]<180,"Medium",Table1[[#This Row],[Duration]]<=240,"Long",TRUE,"Seasons")} -> Medium | P186: Children & Family Movies, Sports Movies
A187: s403 | B187: Movie | C187: The Last Letter From Your Lover | D187: Augustine Frizzell | E187: Shailene Woodley, Felicity Jones, Callum Turner, Joe Alwyn, Nabhaan Rizwan, Ncuti Gatwa, Emma Appleton, Christian Brassington, Alice Orr-Ewing, Lee Knight, Zoe Boyle, Ben Cross, Diana Kent | F187: United Kingdom | G187: July 23, 2021 | H187: 2021 | I187: 2021 | J187: =YEAR(TODAY())-Table1[[#This Row],[Release_year]] -> 5 | K187: TV-MA | L187: =_xlfn.XLOOKUP(Table1[[#This Row],[Rating]],Ratings!A$2:A$15,Ratings!B$2:B$15) -> Adult | M187: =_xlfn.XLOOKUP(Table1[[#This Row],[Rating Category]],Recommendation!A$2:A$6,Recommendation!B$2:B$6) -> Restricted | N187: 111 | O187: {=_xlfn.IFS(Table1[[#This Row],[Duration]]<90,"Short",Table1[[#This Row],[Duration]]<180,"Medium",Table1[[#This Row],[Duration]]<=240,"Long",TRUE,"Seasons")} -> Medium | P187: Dramas, Romantic Movies
A188: s411 | B188: Movie | C188: Chhota Bheem And The Broken Amulet | D188: Rajiv Chilaka | E188: Vatsal Dubey, Julie Tejwani, Rupa Bhimani, Jigna Bhardwaj, Rajesh Kava, Mousam, Swapnil | F188: India | G188: July 22, 2021 | H188: 2021 | I188: 2013 | J188: =YEAR(TODAY())-Table1[[#This Row],[Release_year]] -> 13 | K188: TV-Y7 | L188: =_xlfn.XLOOKUP(Table1[[#This Row],[Rating]],Ratings!A$2:A$15,Ratings!B$2:B$15) -> Kids | M188: =_xlfn.XLOOKUP(Table1[[#This Row],[Rating Category]],Recommendation!A$2:A$6,Recommendation!B$2:B$6) -> Safe | N188: 64 | O188: {=_xlfn.IFS(Table1[[#This Row],[Duration]]<90,"Short",Table1[[#This Row],[Duration]]<180,"Medium",Table1[[#This Row],[Duration]]<=240,"Long",TRUE,"Seasons")} -> Short | P188: Children & Family Movies
A189: s416 | B189: Movie | C189: Chhota Bheem aur Krishna | D189: Rajiv Chilaka | E189: Vatsal Dubey, Julie Tejwani, Rupa Bhimani, Jigna Bhardwaj, Rajesh Kava, Arun Shekher, Sanchit Wartak | F189: India | G189: July 22, 2021 | H189: 2021 | I189: 2009 | J189: =YEAR(TODAY())-Table1[[#This Row],[Release_year]] -> 17 | K189: TV-Y7 | L189: =_xlfn.XLOOKUP(Table1[[#This Row],[Rating]],Ratings!A$2:A$15,Ratings!B$2:B$15) -> Kids | M189: =_xlfn.XLOOKUP(Table1[[#This Row],[Rating Category]],Recommendation!A$2:A$6,Recommendation!B$2:B$6) -> Safe | N189: 68 | O189: {=_xlfn.IFS(Table1[[#This Row],[Duration]]<90,"Short",Table1[[#This Row],[Duration]]<180,"Medium",Table1[[#This Row],[Duration]]<=240,"Long",TRUE,"Seasons")} -> Short | P189: Children & Family Movies
A190: s427 | B190: Movie | C190: Cousins | D190: Ainsley Gardiner, Briar Grace-Smith | E190: Rachel House, Briar Grace-Smith, Tanea Heke, Tioreore Ngatai-Melbourne, Ana Scotney, Hariata Moriarty, Chelsie Preston Crayford, Sylvia Rands | F190: New Zealand | G190: July 22, 2021 | H190: 2021 | I190: 2021 | J190: =YEAR(TODAY())-Table1[[#This Row],[Release_year]] -> 5 | K190: TV-MA | L190: =_xlfn.XLOOKUP(Table1[[#This Row],[Rating]],Ratings!A$2:A$15,Ratings!B$2:B$15) -> Adult | M190: =_xlfn.XLOOKUP(Table1[[#This Row],[Rating Category]],Recommendation!A$2:A$6,Recommendation!B$2:B$6) -> Restricted | N190: 99 | O190: {=_xlfn.IFS(Table1[[#This Row],[Duration]]<90,"Short",Table1[[#This Row],[Duration]]<180,"Medium",Table1[[#This Row],[Duration]]<=240,"Long",TRUE,"Seasons")} -> Medium | P190: Dramas
A191: s430 | B191: Movie | C191: Sanitation Day | D191: Seyi Babatope | E191: Blossom Chukwujekwu, Elozonam Ogbolu, Nse Ikpe-Etim, Belinda Effah, Saeed Mohammed, Chukwuemeka Okoroafor, Kunle Fawole, Chris Okagbue, Adebayo Salami, Charles Inojie, Elvina Ibru, Tobi Bakare | F191: Nigeria | G191: July 21, 2021 | H191: 2021 | I191: 2020 | J191: =YEAR(TODAY())-Table1[[#This Row],[Release_year]] -> 6 | K191: TV-14 | L191: =_xlfn.XLOOKUP(Table1[[#This Row],[Rating]],Ratings!A$2:A$15,Ratings!B$2:B$15) -> Teen | M191: =_xlfn.XLOOKUP(Table1[[#This Row],[Rating Category]],Recommendation!A$2:A$6,Recommendation!B$2:B$6) -> Guidance | N191: 105 | O191: {=_xlfn.IFS(Table1[[#This Row],[Duration]]<90,"Short",Table1[[#This Row],[Duration]]<180,"Medium",Table1[[#This Row],[Duration]]<=240,"Long",TRUE,"Seasons")} -> Medium | P191: Dramas, International Movies, Thrillers
A192: s434 | B192: Movie | C192: Milkwater | D192: Morgan Ingari | E192: Molly Bernard, Patrick Breen, Robin de Jess, Ava Eisenson, Ade Otukoya | F192: United States | G192: July 20, 2021 | H192: 2021 | I192: 2020 | J192: =YEAR(TODAY())-Table1[[#This Row],[Release_year]] -> 6 | K192: TV-MA | L192: =_xlfn.XLOOKUP(Table1[[#This Row],[Rating]],Ratings!A$2:A$15,Ratings!B$2:B$15) -> Adult | M192: =_xlfn.XLOOKUP(Table1[[#This Row],[Rating Category]],Recommendation!A$2:A$6,Recommendation!B$2:B$6) -> Restricted | N192: 102 | O192: {=_xlfn.IFS(Table1[[#This Row],[Duration]]<90,"Short",Table1[[#This Row],[Duration]]<180,"Medium",Table1[[#This Row],[Duration]]<=240,"Long",TRUE,"Seasons")} -> Medium | P192: Comedies, Dramas, Independent Movies
A193: s437 | B193: Movie | C193: The Tambour of Retribution | D193: Abdulaziz Alshlahei | E193: Faisal Al Dokhei, Adwa Fahad, Muhand Alsaleh, Rawya Ahmed, Ajeba Aldosary, Aly Ibrahim, Samer Elkhal, Hashem Hawsawi, Ibrahim Mesisebi, Shabib Alkhaleefa, Abdulateif Saud, Nada Alshehry, Dhay Nasser | F193: Saudi Arabia | G193: July 19, 2021 | H193: 2021 | I193: 2021 | J193: =YEAR(TODAY())-Table1[[#This Row],[Release_year]] -> 5 | K193: TV-14 | L193: =_xlfn.XLOOKUP(Table1[[#This Row],[Rating]],Ratings!A$2:A$15,Ratings!B$2:B$15) -> Teen | M193: =_xlfn.XLOOKUP(Table1[[#This Row],[Rating Category]],Recommendation!A$2:A$6,Recommendation!B$2:B$6) -> Guidance | N193: 91 | O193: {=_xlfn.IFS(Table1[[#This Row],[Duration]]<90,"Short",Table1[[#This Row],[Duration]]<180,"Medium",Table1[[#This Row],[Duration]]<=240,"Long",TRUE,"Seasons")} -> Medium | P193: Dramas, International Movies, Romantic Movies
A194: s438 | B194: Movie | C194: Cosmic Sin | D194: Edward Drake | E194: Frank Grillo, Bruce Willis, Brandon Thomas Lee, Corey Large, Perrey Reeves, C.J. Perry, Lochlyn Munro, Costas Mandylor, Adelaide Kane, Eva De Dominici, Sarah May Sommers, Trevor Gretzky | F194: United States | G194: July 17, 2021 | H194: 2021 | I194: 2021 | J194: =YEAR(TODAY())-Table1[[#This Row],[Release_year]] -> 5 | K194: R | L194: =_xlfn.XLOOKUP(Table1[[#This Row],[Rating]],Ratings!A$2:A$15,Ratings!B$2:B$15) -> Adult | M194: =_xlfn.XLOOKUP(Table1[[#This Row],[Rating Category]],Recommendation!A$2:A$6,Recommendation!B$2:B$6) -> Restricted | N194: 88 | O194: {=_xlfn.IFS(Table1[[#This Row],[Duration]]<90,"Short",Table1[[#This Row],[Duration]]<180,"Medium",Table1[[#This Row],[Duration]]<=240,"Long",TRUE,"Seasons")} -> Short | P194: Action & Adventure
... A214: s503 | B214: Movie | C214: Tango With Me | D214: Mahmood Ali-Balogun | E214: Genevieve Nnaji, Joseph Benjamin, Joke Silva, Tina Mba, Ahmed Yerima, Bimbo Manuel, Sade Alder-Hayes | F214: Nigeria | G214: July 7, 2021 | H214: 2021 | I214: 2010 | J214: =YEAR(TODAY())-Table1[[#This Row],[Release_year]] -> 16 | K214: TV-14 | L214: =_xlfn.XLOOKUP(Table1[[#This Row],[Rating]],Ratings!A$2:A$15,Ratings!B$2:B$15) -> Teen | M214: =_xlfn.XLOOKUP(Table1[[#This Row],[Rating Category]],Recommendation!A$2:A$6,Recommendation!B$2:B$6) -> Guidance | N214: 104 | O214: {=_xlfn.IFS(Table1[[#This Row],[Duration]]<90,"Short",Table1[[#This Row],[Duration]]<180,"Medium",Table1[[#This Row],[Duration]]<=240,"Long",TRUE,"Seasons")} -> Medium | P214: Dramas, International Movies, Romantic Movies
A215: s504 | B215: TV Show | C215: The Mire | D215: Jan Holoubek | E215: Andrzej Seweryn, Dawid Ogrodnik, Zofia Wichacz, Magdalena Walach, Piotr Fronczewski, Agnieszka ulewska, Ireneusz Czop, Zbigniew Walery, Jacek Beler, Nel Kaczmarek | F215: Poland | G215: July 7, 2021 | H215: 2021 | I215: 2021 | J215: =YEAR(TODAY())-Table1[[#This Row],[Release_year]] -> 5 | K215: TV-MA | L215: =_xlfn.XLOOKUP(Table1[[#This Row],[Rating]],Ratings!A$2:A$15,Ratings!B$2:B$15) -> Adult | M215: =_xlfn.XLOOKUP(Table1[[#This Row],[Rating Category]],Recommendation!A$2:A$6,Recommendation!B$2:B$6) -> Restricted | N215: 2 Seasons | O215: {=_xlfn.IFS(Table1[[#This Row],[Duration]]<90,"Short",Table1[[#This Row],[Duration]]<180,"Medium",Table1[[#This Row],[Duration]]<=240,"Long",TRUE,"Seasons")} -> Seasons | P215: Crime TV Shows, International TV Shows, TV Dramas
A216: s507 | B216: Movie | C216: This Little Love Of Mine | D216: Christine Luby | E216: Saskia Hampele, Liam McIntyre, Lynn Gilmartin, Craig Horner | F216: Australia | G216: July 7, 2021 | H216: 2021 | I216: 2021 | J216: =YEAR(TODAY())-Table1[[#This Row],[Release_year]] -> 5 | K216: TV-G | L216: =_xlfn.XLOOKUP(Table1[[#This Row],[Rating]],Ratings!A$2:A$15,Ratings!B$2:B$15) -> Family | M216: =_xlfn.XLOOKUP(Table1[[#This Row],[Rating Category]],Recommendation!A$2:A$6,Recommendation!B$2:B$6) -> Guidance | N216: 92 | O216: {=_xlfn.IFS(Table1[[#This Row],[Duration]]<90,"Short",Table1[[#This Row],[Duration]]<180,"Medium",Table1[[#This Row],[Duration]]<=240,"Long",TRUE,"Seasons")} -> Medium | P216: International Movies, Romantic Movies
A217: s509 | B217: Movie | C217: A Land Imagined | D217: Yeo Siew Hua | E217: Peter Yu, Liu Xiaoyi, Guo Yue, Ishtiaque Zico, Jack Tan | F217: France, Netherlands, Singapore | G217: July 6, 2021 | H217: 2021 | I217: 2019 | J217: =YEAR(TODAY())-Table1[[#This Row],[Release_year]] -> 7 | K217: TV-MA | L217: =_xlfn.XLOOKUP(Table1[[#This Row],[Rating]],Ratings!A$2:A$15,Ratings!B$2:B$15) -> Adult | M217: =_xlfn.XLOOKUP(Table1[[#This Row],[Rating Category]],Recommendation!A$2:A$6,Recommendation!B$2:B$6) -> Restricted | N217: 95 | O217: {=_xlfn.IFS(Table1[[#This Row],[Duration]]<90,"Short",Table1[[#This Row],[Duration]]<180,"Medium",Table1[[#This Row],[Duration]]<=240,"Long",TRUE,"Seasons")} -> Medium | P217: Dramas, International Movies
A218: s519 | B218: Movie | C218: Har Kisse Ke Hisse: Kaamyaab | D218: Hardik Mehta | E218: Sanjay Mishra, Deepak Dobriyal, Sarika Singh, Isha Talwar, Avtar Gill, Kaurwakee Vashistha, Amitabh Srivastava, Vikas Verma | F218: India | G218: July 6, 2021 | H218: 2021 | I218: 2020 | J218: =YEAR(TODAY())-Table1[[#This Row],[Release_year]] -> 6 | K218: TV-14 | L218: =_xlfn.XLOOKUP(Table1[[#This Row],[Rating]],Ratings!A$2:A$15,Ratings!B$2:B$15) -> Teen | M218: =_xlfn.XLOOKUP(Table1[[#This Row],[Rating Category]],Recommendation!A$2:A$6,Recommendation!B$2:B$6) -> Guidance | N218: 105 | O218: {=_xlfn.IFS(Table1[[#This Row],[Duration]]<90,"Short",Table1[[#This Row],[Duration]]<180,"Medium",Table1[[#This Row],[Duration]]<=240,"Long",TRUE,"Seasons")} -> Medium | P218: Dramas, International Movies
A219: s529 | B219: Movie | C219: Rehmataan | D219: Rajveer Singh Maan, Harpeet Singh | E219: Guggu Gill, Sukhjinder Shera, Surinder Shinda, Deep Dhillon, Jasmine Jassi, Gurvinder Brar, Razia Sukhvir, Raj Virk | F219: India | G219: July 6, 2021 | H219: 2021 | I219: 2012 | J219: =YEAR(TODAY())-Table1[[#This Row],[Release_year]] -> 14 | K219: TV-14 | L219: =_xlfn.XLOOKUP(Table1[[#This Row],[Rating]],Ratings!A$2:A$15,Ratings!B$2:B$15) -> Teen | M219: =_xlfn.XLOOKUP(Table1[[#This Row],[Rating Category]],Recommendation!A$2:A$6,Recommendation!B$2:B$6) -> Guidance | N219: 116 | O219: {=_xlfn.IFS(Table1[[#This Row],[Duration]]<90,"Short",Table1[[#This Row],[Duration]]<180,"Medium",Table1[[#This Row],[Duration]]<=240,"Long",TRUE,"Seasons")} -> Medium | P219: Dramas, International Movies, Romantic Movies
A220: s530 | B220: Movie | C220: Return of the Prodigal Son | D220: Youssef Chahine | E220: Majida El Roumi, Souheir El Morshidy, Shoukry Sarhan, Huda Sultan, Mahmoud El Meleigy, Ahmad Mehrez, Hesham Selim | F220: Egypt | G220: July 6, 2021 | H220: 2021 | I220: 1976 | J220: =YEAR(TODAY())-Table1[[#This Row],[Release_year]] -> 50 | K220: TV-MA | L220: =_xlfn.XLOOKUP(Table1[[#This Row],[Rating]],Ratings!A$2:A$15,Ratings!B$2:B$15) -> Adult | M220: =_xlfn.XLOOKUP(Table1[[#This Row],[Rating Category]],Recommendation!A$2:A$6,Recommendation!B$2:B$6) -> Restricted | N220: 124 | O220: {=_xlfn.IFS(Table1[[#This Row],[Duration]]<90,"Short",Table1[[#This Row],[Duration]]<180,"Medium",Table1[[#This Row],[Duration]]<=240,"Long",TRUE,"Seasons")} -> Medium | P220: Dramas, International Movies
A221: s532 | B221: Movie | C221: Rise: Ini Kalilah | D221: Saw Teong Hin, Nik Amir Mustapha, M.S. Prem Nath | E221: Remy Ishak, Mira Filzah, Jack Tan, Sangeeta Krishnasamy, Shashi Tharan, Mark O'Dea, Jenn Chia, Sharifah Sakinah | F221: Malaysia | G221: July 6, 2021 | H221: 2021 | I221: 2018 | J221: =YEAR(TODAY())-Table1[[#This Row],[Release_year]] -> 8 | K221: TV-PG | L221: =_xlfn.XLOOKUP(Table1[[#This Row],[Rating]],Ratings!A$2:A$15,Ratings!B$2:B$15) -> Family | M221: =_xlfn.XLOOKUP(Table1[[#This Row],[Rating Category]],Recommendation!A$2:A$6,Recommendation!B$2:B$6) -> Guidance | N221: 101 | O221: {=_xlfn.IFS(Table1[[#This Row],[Duration]]<90,"Short",Table1[[#This Row],[Duration]]<180,"Medium",Table1[[#This Row],[Duration]]<=240,"Long",TRUE,"Seasons")} -> Medium | P221: Dramas, International Movies
A222: s535 | B222: Movie | C222: Si Doel the Movie 2 | D222: Rano Karno | E222: Maudy Koesnaedi, Rano Karno, Cornelia Agatha, Mandra Naih, Aminah Tjendrakasih, Suty Karno, Adam Jagwani | F222: Indonesia | G222: July 6, 2021 | H222: 2021 | I222: 2019 | J222: =YEAR(TODAY())-Table1[[#This Row],[Release_year]] -> 7 | K222: TV-G | L222: =_xlfn.XLOOKUP(Table1[[#This Row],[Rating]],Ratings!A$2:A$15,Ratings!B$2:B$15) -> Family | M222: =_xlfn.XLOOKUP(Table1[[#This Row],[Rating Category]],Recommendation!A$2:A$6,Recommendation!B$2:B$6) -> Guidance | N222: 95 | O222: {=_xlfn.IFS(Table1[[#This Row],[Duration]]<90,"Short",Table1[[#This Row],[Duration]]<180,"Medium",Table1[[#This Row],[Duration]]<=240,"Long",TRUE,"Seasons")} -> Medium | P222: Dramas, International Movies
A223: s542 | B223: Movie | C223: Truckbhar Swapna | D223: Pramod Pawar | E223: Makrand Deshpande, Kranti Redkar, Mukesh Rishi, Manoj Joshi, Smita Tambe, Aaditi Pohankar, Sahil Gilbile, Jyoti Joshi | F223: India | G223: July 6, 2021 | H223: 2021 | I223: 2018 | J223: =YEAR(TODAY())-Table1[[#This Row],[Release_year]] -> 8 | K223: TV-14 | L223: =_xlfn.XLOOKUP(Table1[[#This Row],[Rating]],Ratings!A$2:A$15,Ratings!B$2:B$15) -> Teen | M223: =_xlfn.XLOOKUP(Table1[[#This Row],[Rating Category]],Recommendation!A$2:A$6,Recommendation!B$2:B$6) -> Guidance | N223: 128 | O223: {=_xlfn.IFS(Table1[[#This Row],[Duration]]<90,"Short",Table1[[#This Row],[Duration]]<180,"Medium",Table1[[#This Row],[Duration]]<=240,"Long",TRUE,"Seasons")} -> Medium | P223: Comedies, Dramas, International Movies
A224: s543 | B224: Movie | C224: Ujala | D224: Naresh Saigal | E224: Mala Sinha, Shammi Kapoor, Raaj Kumar, Leela Chitnis, Dhumal, Kumkum | F224: India | G224: July 6, 2021 | H224: 2021 | I224: 1959 | J224: =YEAR(TODAY())-Table1[[#This Row],[Release_year]] -> 67 | K224: TV-14 | L224: =_xlfn.XLOOKUP(Table1[[#This Row],[Rating]],Ratings!A$2:A$15,Ratings!B$2:B$15) -> Teen | M224: =_xlfn.XLOOKUP(Table1[[#This Row],[Rating Category]],Recommendation!A$2:A$6,Recommendation!B$2:B$6) -> Guidance | N224: 143 | O224: {=_xlfn.IFS(Table1[[#This Row],[Duration]]<90,"Short",Table1[[#This Row],[Duration]]<180,"Medium",Table1[[#This Row],[Duration]]<=240,"Long",TRUE,"Seasons")} -> Medium | P224: Dramas, International Movies
A225: s552 | B225: Movie | C225: Haseen Dillruba | D225: Vinil Mathew | E225: Taapsee Pannu, Vikrant Massey, Harshvardhan Rane, Aditya Srivastava, Ashish Verma, Yamini Das, Daya Shankar Pandey | F225: India | G225: July 2, 2021 | H225: 2021 | I225: 2021 | J225: =YEAR(TODAY())-Table1[[#This Row],[Release_year]] -> 5 | K225: TV-MA | L225: =_xlfn.XLOOKUP(Table1[[#This Row],[Rating]],Ratings!A$2:A$15,Ratings!B$2:B$15) -> Adult | M225: =_xlfn.XLOOKUP(Table1[[#This Row],[Rating Category]],Recommendation!A$2:A$6,Recommendation!B$2:B$6) -> Restricted | N225: 136 | O225: {=_xlfn.IFS(Table1[[#This Row],[Duration]]<90,"Short",Table1[[#This Row],[Duration]]<180,"Medium",Table1[[#This Row],[Duration]]<=240,"Long",TRUE,"Seasons")} -> Medium | P225: International Movies, Romantic Movies, Thrillers
A226: s555 | B226: Movie | C226: RattleSnake - The Ahanna Story | D226: Ramsey Nouah | E226: Stan Nze, Osas Ighodaro, Bucci Franklin, Odera Adimorah, Efa Iwara, Emeka Nwagbaraocha, Elma Mbadiwe, Norbert Young, Brutus Richard, Chinyere Wilfred, Sonny McDon, Chiwetalu Agu | F226: Nigeria | G226: July 2, 2021 | H226: 2021 | I226: 2020 | J226: =YEAR(TODAY())-Table1[[#This Row],[Release_year]] -> 6 | K226: TV-MA | L226: =_xlfn.XLOOKUP(Table1[[#This Row],[Rating]],Ratings!A$2:A$15,Ratings!B$2:B$15) -> Adult | M226: =_xlfn.XLOOKUP(Table1[[#This Row],[Rating Category]],Recommendation!A$2:A$6,Recommendation!B$2:B$6) -> Restricted | N226: 136 | O226: {=_xlfn.IFS(Table1[[#This Row],[Duration]]<90,"Short",Table1[[#This Row],[Duration]]<180,"Medium",Table1[[#This Row],[Duration]]<=240,"Long",TRUE,"Seasons")} -> Medium | P226: Dramas, International Movies, Thrillers
A227: s556 | B227: Movie | C227: Snowpiercer | D227: Bong Joon Ho | E227: Chris Evans, Song Kang-ho, Ed Harris, John Hurt, Tilda Swinton, Jamie Bell, Octavia Spencer, Ewen Bremner, Alison Pill, Adnan Haskovic, Vlad Ivanov, Ko A-sung, Luke Pasqualino | F227: South Korea, Czech Republic | G227: July 2, 2021 | H227: 2021 | I227: 2013 | J227: =YEAR(TODAY())-Table1[[#This Row],[Release_year]] -> 13 | K227: R | L227: =_xlfn.XLOOKUP(Table1[[#This Row],[Rating]],Ratings!A$2:A$15,Ratings!B$2:B$15) -> Adult | M227: =_xlfn.XLOOKUP(Table1[[#This Row],[Rating Category]],Recommendation!A$2:A$6,Recommendation!B$2:B$6) -> Restricted | N227: 126 | O227: {=_xlfn.IFS(Table1[[#This Row],[Duration]]<90,"Short",Table1[[#This Row],[Duration]]<180,"Medium",Table1[[#This Row],[Duration]]<=240,"Long",TRUE,"Seasons")} -> Medium | P227: Action & Adventure, Cult Movies, International Movies
... A289: s657 | B289: Movie | C289: Love Is a Story | D289: Cristina Jacob | E289: Raluca Aprodu, Drago Bucur, Ducu Darie | F289: Romania | G289: June 21, 2021 | H289: 2021 | I289: 2015 | J289: =YEAR(TODAY())-Table1[[#This Row],[Release_year]] -> 11 | K289: TV-MA | L289: =_xlfn.XLOOKUP(Table1[[#This Row],[Rating]],Ratings!A$2:A$15,Ratings!B$2:B$15) -> Adult | M289: =_xlfn.XLOOKUP(Table1[[#This Row],[Rating Category]],Recommendation!A$2:A$6,Recommendation!B$2:B$6) -> Restricted | N289: 105 | O289: {=_xlfn.IFS(Table1[[#This Row],[Duration]]<90,"Short",Table1[[#This Row],[Duration]]<180,"Medium",Table1[[#This Row],[Duration]]<=240,"Long",TRUE,"Seasons")} -> Medium | P289: International Movies, Music & Musicals, Romantic Movies
A290: s677 | B290: TV Show | C290: Riverdale | D290: Rob Seidenglanz | E290: K.J. Apa, Lili Reinhart, Camila Mendes, Cole Sprouse, Marisol Nichols, Madelaine Petsch, Ashleigh Murray, Mdchen Amick, Luke Perry, Casey Cott, Charles Melton, Mark Consuelos, Lochlyn Munro, Peter Bryant, Colin Lawrence, Molly Ringwald, Asha Bromfield, Barclay Hope, Hayley Law, Martin Cummins, Sarah Habel, Nathalie Boltt, Skeet Ulrich | F290: United States | G290: June 19, 2021 | H290: 2021 | I290: 2019 | J290: =YEAR(TODAY())-Table1[[#This Row],[Release_year]] -> 7 | K290: TV-14 | L290: =_xlfn.XLOOKUP(Table1[[#This Row],[Rating]],Ratings!A$2:A$15,Ratings!B$2:B$15) -> Teen | M290: =_xlfn.XLOOKUP(Table1[[#This Row],[Rating Category]],Recommendation!A$2:A$6,Recommendation!B$2:B$6) -> Guidance | N290: 4 Seasons | O290: {=_xlfn.IFS(Table1[[#This Row],[Duration]]<90,"Short",Table1[[#This Row],[Duration]]<180,"Medium",Table1[[#This Row],[Duration]]<=240,"Long",TRUE,"Seasons")} -> Seasons | P290: Crime TV Shows, TV Dramas, TV Mysteries
A291: s682 | B291: TV Show | C291: They've Gotta Have Us | D291: Simon Frederick | E291: Debbie Allen, Harry Belafonte, John Boyega, Diahann Carroll, Ernest R. Dickerson, Laurence Fishburne, Nelson George, Whoopi Goldberg, Cuba Gooding Jr., LilRel Howery, Barry Jenkins, Kasi Lemmons, David Oyelowo, Robert Townsend, Jesse Williams | F291: United Kingdom | G291: June 19, 2021 | H291: 2021 | I291: 2018 | J291: =YEAR(TODAY())-Table1[[#This Row],[Release_year]] -> 8 | K291: TV-MA | L291: =_xlfn.XLOOKUP(Table1[[#This Row],[Rating]],Ratings!A$2:A$15,Ratings!B$2:B$15) -> Adult | M291: =_xlfn.XLOOKUP(Table1[[#This Row],[Rating Category]],Recommendation!A$2:A$6,Recommendation!B$2:B$6) -> Restricted | N291: 1 Season | O291: {=_xlfn.IFS(Table1[[#This Row],[Duration]]<90,"Short",Table1[[#This Row],[Duration]]<180,"Medium",Table1[[#This Row],[Duration]]<=240,"Long",TRUE,"Seasons")} -> Seasons | P291: British TV Shows, Docuseries
A292: s686 | B292: Movie | C292: Fatherhood | D292: Paul Weitz | E292: Kevin Hart, Alfre Woodard, Lil Rel Howery, DeWanda Wise, Frankie Faison, Anthony Carrigan, Paul Reiser, Melody Hurd | F292: United States | G292: June 18, 2021 | H292: 2021 | I292: 2021 | J292: =YEAR(TODAY())-Table1[[#This Row],[Release_year]] -> 5 | K292: PG-13 | L292: =_xlfn.XLOOKUP(Table1[[#This Row],[Rating]],Ratings!A$2:A$15,Ratings!B$2:B$15) -> Teen | M292: =_xlfn.XLOOKUP(Table1[[#This Row],[Rating Category]],Recommendation!A$2:A$6,Recommendation!B$2:B$6) -> Guidance | N292: 111 | O292: {=_xlfn.IFS(Table1[[#This Row],[Duration]]<90,"Short",Table1[[#This Row],[Duration]]<180,"Medium",Table1[[#This Row],[Duration]]<=240,"Long",TRUE,"Seasons")} -> Medium | P292: Dramas
A293: s689 | B293: Movie | C293: Kambili: The Whole 30 Yards | D293: Kayode Kasum | E293: Nancy Isime, Jide Kene Achufusi, Sharon Ooja, Mawuli Gavor, Venita Akpofure, Koye Kekere Ekun, Elvina Ibru, Uzor Arukwe, Toyin Abraham | F293: Nigeria | G293: June 18, 2021 | H293: 2021 | I293: 2020 | J293: =YEAR(TODAY())-Table1[[#This Row],[Release_year]] -> 6 | K293: TV-14 | L293: =_xlfn.XLOOKUP(Table1[[#This Row],[Rating]],Ratings!A$2:A$15,Ratings!B$2:B$15) -> Teen | M293: =_xlfn.XLOOKUP(Table1[[#This Row],[Rating Category]],Recommendation!A$2:A$6,Recommendation!B$2:B$6) -> Guidance | N293: 119 | O293: {=_xlfn.IFS(Table1[[#This Row],[Duration]]<90,"Short",Table1[[#This Row],[Duration]]<180,"Medium",Table1[[#This Row],[Duration]]<=240,"Long",TRUE,"Seasons")} -> Medium | P293: Comedies, International Movies, Romantic Movies
...

Sheet Recommendation
A1: Category | B1: Recommendation
A2: Kids | B2: Safe
A3: Family | B3: Guidance
A4: Teen | B4: Guidance
A5: Adult | B5: Restricted
A6: Not Rated | B6: Guidance

Sheet Ratings
A1: Ratings | B1: Rating Category
A2: TV-Y | B2: Kids
A3: TV-G | B3: Family
A4: TV-14 | B4: Teen
A5: TV-MA | B5: Adult
A6: PG | B6: Family
A7: PG-13 | B7: Teen
A8: R | B8: Adult
A9: TV-PG | B9: Family
A10: G | B10: Family
A11: NC-17 | B11: Adult
A12: NR | B12: Not Rated
... A15: UR | B15: Not Rated
